Verilog repository/Design Files/Argmaax_output.v
`timescale 1ns / 1ps
//////////////////////////////////////////////////////////////////////////////////
// Company: University of Manchester
// Engineer: Lewis Hunton
// 
// Create Date:    02:47:06 12/15/2025 
// Design Name: 
// Module Name:    Argmaax_output 
// Project Name: FPGA Implementation of a MLP Artificial Neural Network Optimised for Size
// Target Devices: XC3S1500 Spartan-3
// Tool versions: Xilinx 14.2
// Description: Argmax block
//
// Dependencies: 
//
// Revision: 
// Revision 0.01 - File Created
// Additional Comments: 
//
//////////////////////////////////////////////////////////////////////////////////
module Argmaax_output(
    input wire Clk,
    input wire Reset,

	 input wire ValidIn,
	 input wire [79:0] DataIn,
	 
	 output reg [3:0] Output,
	 output reg Valid
    );

reg [7:0] Stage1Max [0:4];
reg [3:0] Stage1Idx [0:4];
reg [79:0] Stage1Data;

reg Stage1Valid;

reg [7:0] Stage2Max [0:2];
reg [3:0] Stage2Idx [0:2];

reg Stage2Valid;

reg [7:0] Stage3Max [0:1];
reg [3:0] Stage3Idx [0:1];

reg Stage3Valid;

reg [7:0] Stage4Max;
reg [3:0] Stage4Idx;

reg Stage4Valid;

integer i;

always @(posedge Clk) begin
	if(Reset) begin
		Stage1Valid <= 1'b0;
        for(i = 0; i < 5; i = i + 1) begin
            Stage1Max[i] <= 8'b0;
            Stage1Idx[i] <= 4'b0;
        end
	end else begin
		Stage1Valid <= ValidIn;
		Stage1Data <= DataIn;
		
		if (ValidIn) begin
		//Pair 1
			if(DataIn[7:0] > DataIn[15:8]) begin
                Stage1Max[0] <= DataIn[7:0];
                Stage1Idx[0] <= 4'd0;
            end else begin
                Stage1Max[0] <= DataIn[15:8];
                Stage1Idx[0] <= 4'd1;
            end
				
		//pair 2
			if(DataIn[23:16] > DataIn[31:24]) begin
                Stage1Max[1] <= DataIn[23:16];
                Stage1Idx[1] <= 4'd2;
            end else begin
                Stage1Max[1] <= DataIn[31:24];
                Stage1Idx[1] <= 4'd3;
            end
				
			//pair 3
			if(DataIn[39:32] > DataIn[47:40]) begin
                Stage1Max[2] <= DataIn[39:32];
                Stage1Idx[2] <= 4'd4;
            end else begin
                Stage1Max[2] <= DataIn[47:40];
                Stage1Idx[2] <= 4'd5;
            end
			
			//pair 4
			if(DataIn[55:48] > DataIn[63:56]) begin
                Stage1Max[3] <= DataIn[55:48];
                Stage1Idx[3] <= 4'd6;
            end else begin
                Stage1Max[3] <= DataIn[63:56];
                Stage1Idx[3] <= 4'd7;
            end
			
			//pair 5
			if(DataIn[71:64] > DataIn[79:72]) begin
                Stage1Max[4] <= DataIn[71:64];
                Stage1Idx[4] <= 4'd8;
            end else begin
                Stage1Max[4] <= DataIn[79:72];
                Stage1Idx[4] <= 4'd9;
            end
			end
		end
	end


always @(posedge Clk) begin
	if(Reset) begin
		Stage2Valid <= 1'b0;
        for(i = 0; i < 3; i = i + 1) begin
            Stage2Max[i] <= 8'b0;
            Stage2Idx[i] <= 4'b0;
        end
	end else begin
		Stage2Valid <= Stage1Valid;
		
		if (Stage1Valid) begin
			if(Stage1Max[0] > Stage1Max[1]) begin
				Stage2Max[0] <= Stage1Max[0];
            Stage2Idx[0] <= Stage1Idx[0];
         end else begin
            Stage2Max[0] <= Stage1Max[1];
				Stage2Idx[0] <= Stage1Idx[1];
         end
				
			if(Stage1Max[2] > Stage1Max[3]) begin
            Stage2Max[1] <= Stage1Max[2];
            Stage2Idx[1] <= Stage1Idx[2];
         end else begin
            Stage2Max[1] <= Stage1Max[3];
            Stage2Idx[1] <= Stage1Idx[3];
         end
				
			Stage2Max[2] <= Stage1Max[4];
			Stage2Idx[2] <= Stage1Idx[4];
		end
	end
end

always @(posedge Clk) begin
	if(Reset) begin
		Stage3Valid <= 1'b0;
        for(i = 0; i < 2; i = i + 1) begin
            Stage3Max[i] <= 8'b0;
            Stage3Idx[i] <= 4'b0;
        end
	end else begin
		Stage3Valid <= Stage2Valid;
		
		if (Stage2Valid) begin
			if(Stage2Max[0] > Stage2Max[1]) begin
				Stage3Max[0] <= Stage2Max[0];
            Stage3Idx[0] <= Stage2Idx[0];
         end else begin
            Stage3Max[0] <= Stage2Max[1];
				Stage3Idx[0] <= Stage2Idx[1];
         end
				
			Stage3Max[1] <= Stage2Max[2];
			Stage3Idx[1] <= Stage2Idx[2];
		end
	end
end

always @(posedge Clk) begin
	if(Reset) begin
		Stage4Valid <= 1'b0;
		Stage4Max <= 8'b0;
		Stage4Idx <= 4'b0;
	end else begin
		Stage4Valid <= Stage3Valid;
		
		if (Stage3Valid) begin
			if(Stage3Max[0] > Stage3Max[1]) begin
				Stage4Max <= Stage3Max[0];
            Stage4Idx <= Stage3Idx[0];
         end else begin
            Stage4Max <= Stage3Max[1];
				Stage4Idx <= Stage3Idx[1];
         end
		end
	end
end

always @(posedge Clk) begin
	if(Reset) begin
		Output <= 4'b0;
		Valid <= 1'b0;
	end else begin
		Output <= Stage4Idx;
		Valid <= Stage4Valid;
	end
end

endmodule

Verilog repository/Test Benches/ArgmaxOutput_tb.v
`timescale 1ns / 1ps

////////////////////////////////////////////////////////////////////////////////
// Company: University of Manchester
// Engineer: Lewis Hunton
//
// Create Date:   00:14:25 04/14/2026
// Design Name:   Argmaax_output
// Module Name:   /home/ise/CompleteNeuralNetworkV2/ArgmaxOutput_tb.v
// Project Name:  FPGA Implementation of a MLP Artificial Neural Network Optimised for Size
// Target Device:  XC3S1500 Spartan-3
// Tool versions:  Xilinx 14.2
// Description: Argmax Test Bench
//
// Verilog Test Fixture created by ISE for module: Argmaax_output
//
// Dependencies:
// 
// Revision:
// Revision 0.01 - File Created
// Additional Comments:
// 
////////////////////////////////////////////////////////////////////////////////

module ArgmaxOutput_tb;

	// Inputs
	reg Clk;
	reg Reset;
	reg ValidIn;
	reg [79:0] DataIn;

	// Outputs
	wire [3:0] Output;
	wire Valid;

	// Instantiate the Unit Under Test (UUT)
	Argmaax_output uut (
		.Clk(Clk), 
		.Reset(Reset), 
		.ValidIn(ValidIn), 
		.DataIn(DataIn), 
		.Output(Output), 
		.Valid(Valid)
	);

	//clk
	initial begin
		Clk = 0;
			forever #5 Clk = ~Clk;
	end
	
	function signed [79:0] PackLanes;
		input signed [7:0] v0, v1, v2, v3, v4, v5, v6, v7, v8, v9;
		begin
			PackLanes = {v9, v8, v7, v6, v5, v4, v3, v2, v1, v0};
		end
	endfunction
	
	function signed [3:0] ExpectedArgmax;
		input signed [79:0] In;
		integer i;
		reg signed [7:0] MaxVal;
		begin
			MaxVal = In[7:0];
			ExpectedArgmax = 0;
		
			for (i = 1; i <10; i = i + 1) begin
				if(In[i*8 +: 8] > MaxVal) begin
					MaxVal = In[i*8 +: 8];
					ExpectedArgmax = i[3:0];
				end
			end
		end
	endfunction
	
	task ArgmaxTest;
		input signed [79:0] TestInput;
		reg signed [3:0] Expected;
		integer timeout;
		begin
			Expected = ExpectedArgmax(TestInput);
			
			@(posedge Clk);
			#1;
			DataIn = TestInput;
			ValidIn = 1'b1;
			
			@(posedge Clk);
			#1;
			ValidIn = 1'b0;
			
			@(posedge Valid);
			
			if(Output !== Expected) begin
				$display("FAIL: Input=%h ExpectedIdx=%0d Output=%0d", TestInput, Expected, Output);
				$stop;
			end else begin
				$display("PASS: Input=%h Argmax=%0d", TestInput, Output);
			end
		end
	endtask
	
	integer k;
	
	initial begin
		Reset = 1;
		ValidIn = 0;
		DataIn = 0;
		
		$dumpfile("ArgmaxOutput_tb.vcd");
		$dumpvars(0, ArgmaxOutput_tb);
		
		@(posedge Clk);
		@(posedge Clk);
		Reset = 0;
		@(posedge Clk);
		
		ArgmaxTest(PackLanes(8'd1, 8'd2, 8'd3, 8'd4, 8'd5, 8'd6, 8'd7, 8'd8, 8'd9, 8'd10));
		ArgmaxTest(PackLanes(8'd10, 8'd9, 8'd8, 8'd7, 8'd6, 8'd5, 8'd4, 8'd3, 8'd2, 8'd1));
		ArgmaxTest(PackLanes(8'd1, 8'd2, 8'd3, 8'd4, 8'd99, 8'd5, 8'd6, 8'd7, 8'd8, 8'd9));
		//ArgmaxTest(PackLanes(8'd7, 8'd7, 8'd7, 8'd7, 8'd7, 8'd7, 8'd7, 8'd7, 8'd7, 8'd7)); Test cases where the
		//max value is repeated do not work and hardware correction would be overly expensive
		ArgmaxTest(PackLanes(8'd1, 8'd2, 8'd3, 8'd4, 8'd5, 8'd6, 8'd7, 8'd8, 8'd9, 8'd127));
		
		//repeat random tests
		repeat (20) begin
			ArgmaxTest(PackLanes($random, $random, $random, $random, $random, $random, $random, $random, $random, $random));
		end
		
		$display ("ALL ARGMAX TESTS PASSED");
		$finish;
	end
	
endmodule

Verilog repository/Test Benches/Test Bench Results/ArgmaxOutput_tb.vcd
$date
   Tue Apr 14 01:00:03 2026
$end
$version
  P.20131013
$end
$timescale
  1ps
$end
$scope module ArgmaxOutput_tb $end
$var wire 1 ! Output [3] $end
$var wire 1 " Output [2] $end
$var wire 1 # Output [1] $end
$var wire 1 $ Output [0] $end
$var wire 1 % Valid $end
$var reg 1 & Clk $end
$var reg 1 ' Reset $end
$var reg 1 ( ValidIn $end
$var reg 80 ) DataIn [79:0] $end
$var integer 32 * k $end
$scope function PackLanes $end
$var reg 80 + PackLanes [79:0] $end
$var reg 8 , v0 [7:0] $end
$var reg 8 - v1 [7:0] $end
$var reg 8 . v2 [7:0] $end
$var reg 8 / v3 [7:0] $end
$var reg 8 0 v4 [7:0] $end
$var reg 8 1 v5 [7:0] $end
$var reg 8 2 v6 [7:0] $end
$var reg 8 3 v7 [7:0] $end
$var reg 8 4 v8 [7:0] $end
$var reg 8 5 v9 [7:0] $end
$upscope $end
$scope function ExpectedArgmax $end
$var reg 4 6 ExpectedArgmax [3:0] $end
$var reg 80 7 In [79:0] $end
$var integer 32 8 i $end
$var reg 8 9 MaxVal [7:0] $end
$upscope $end
$scope task ArgmaxTest $end
$var reg 80 : TestInput [79:0] $end
$var reg 4 ; Expected [3:0] $end
$var integer 32 < timeout $end
$upscope $end
$scope module uut $end
$var wire 1 = Clk $end
$var wire 1 > Reset $end
$var wire 1 ? ValidIn $end
$var wire 1 @ DataIn [79] $end
$var wire 1 A DataIn [78] $end
$var wire 1 B DataIn [77] $end
$var wire 1 C DataIn [76] $end
$var wire 1 D DataIn [75] $end
$var wire 1 E DataIn [74] $end
$var wire 1 F DataIn [73] $end
$var wire 1 G DataIn [72] $end
$var wire 1 H DataIn [71] $end
$var wire 1 I DataIn [70] $end
$var wire 1 J DataIn [69] $end
$var wire 1 K DataIn [68] $end
$var wire 1 L DataIn [67] $end
$var wire 1 M DataIn [66] $end
$var wire 1 N DataIn [65] $end
$var wire 1 O DataIn [64] $end
$var wire 1 P DataIn [63] $end
$var wire 1 Q DataIn [62] $end
$var wire 1 R DataIn [61] $end
$var wire 1 S DataIn [60] $end
$var wire 1 T DataIn [59] $end
$var wire 1 U DataIn [58] $end
$var wire 1 V DataIn [57] $end
$var wire 1 W DataIn [56] $end
$var wire 1 X DataIn [55] $end
$var wire 1 Y DataIn [54] $end
$var wire 1 Z DataIn [53] $end
$var wire 1 [ DataIn [52] $end
$var wire 1 \ DataIn [51] $end
$var wire 1 ] DataIn [50] $end
$var wire 1 ^ DataIn [49] $end
$var wire 1 _ DataIn [48] $end
$var wire 1 ` DataIn [47] $end
$var wire 1 a DataIn [46] $end
$var wire 1 b DataIn [45] $end
$var wire 1 c DataIn [44] $end
$var wire 1 d DataIn [43] $end
$var wire 1 e DataIn [42] $end
$var wire 1 f DataIn [41] $end
$var wire 1 g DataIn [40] $end
$var wire 1 h DataIn [39] $end
$var wire 1 i DataIn [38] $end
$var wire 1 j DataIn [37] $end
$var wire 1 k DataIn [36] $end
$var wire 1 l DataIn [35] $end
$var wire 1 m DataIn [34] $end
$var wire 1 n DataIn [33] $end
$var wire 1 o DataIn [32] $end
$var wire 1 p DataIn [31] $end
$var wire 1 q DataIn [30] $end
$var wire 1 r DataIn [29] $end
$var wire 1 s DataIn [28] $end
$var wire 1 t DataIn [27] $end
$var wire 1 u DataIn [26] $end
$var wire 1 v DataIn [25] $end
$var wire 1 w DataIn [24] $end
$var wire 1 x DataIn [23] $end
$var wire 1 y DataIn [22] $end
$var wire 1 z DataIn [21] $end
$var wire 1 { DataIn [20] $end
$var wire 1 | DataIn [19] $end
$var wire 1 } DataIn [18] $end
$var wire 1 ~ DataIn [17] $end
$var wire 1 !! DataIn [16] $end
$var wire 1 "! DataIn [15] $end
$var wire 1 #! DataIn [14] $end
$var wire 1 $! DataIn [13] $end
$var wire 1 %! DataIn [12] $end
$var wire 1 &! DataIn [11] $end
$var wire 1 '! DataIn [10] $end
$var wire 1 (! DataIn [9] $end
$var wire 1 )! DataIn [8] $end
$var wire 1 *! DataIn [7] $end
$var wire 1 +! DataIn [6] $end
$var wire 1 ,! DataIn [5] $end
$var wire 1 -! DataIn [4] $end
$var wire 1 .! DataIn [3] $end
$var wire 1 /! DataIn [2] $end
$var wire 1 0! DataIn [1] $end
$var wire 1 1! DataIn [0] $end
$var reg 4 2! Output [3:0] $end
$var reg 1 3! Valid $end
$var reg 40 4! Stage1Max [7:0] $end
$var reg 20 5! Stage1Idx [3:0] $end
$var reg 80 6! Stage1Data [79:0] $end
$var reg 1 7! Stage1Valid $end
$var reg 24 8! Stage2Max [7:0] $end
$var reg 12 9! Stage2Idx [3:0] $end
$var reg 1 :! Stage2Valid $end
$var reg 16 ;! Stage3Max [7:0] $end
$var reg 8 <! Stage3Idx [3:0] $end
$var reg 1 =! Stage3Valid $end
$var reg 8 >! Stage4Max [7:0] $end
$var reg 4 ?! Stage4Idx [3:0] $end
$var reg 1 @! Stage4Valid $end
$var integer 32 A! i $end
$upscope $end
$upscope $end
$enddefinitions $end
#0
$dumpvars
0=
1>
0&
1'
0(
b0 )
bx *
bx +
bx ,
bx -
bx .
bx /
bx 0
bx 1
bx 2
bx 3
bx 4
bx 5
bx 6
bx 7
bx 8
bx 9
bx :
bx ;
bx <
bx 2!
x3!
bx 4!
bx 5!
bx 6!
x7!
bx 8!
bx 9!
x:!
bx ;!
bx <!
x=!
bx >!
bx ?!
x@!
bx A!
x$
x#
x"
x!
x%
0)!
0(!
0'!
0&!
0%!
0$!
0#!
0"!
0!!
0~
0}
0|
0{
0z
0y
0x
0w
0v
0u
0t
0s
0r
0q
0p
0o
0n
0m
0?
01!
00!
0/!
0.!
0-!
0,!
0+!
0*!
0l
0k
0j
0i
0h
0g
0f
0e
0d
0c
0b
0a
0`
0_
0^
0]
0\
0[
0Z
0Y
0X
0W
0V
0U
0T
0S
0R
0Q
0P
0O
0N
0M
0L
0K
0J
0I
0H
0G
0F
0E
0D
0C
0B
0A
0@
$end
#5000
1=
1&
b0 2!
03!
b0 4!
b0 5!
07!
b0 8!
b0 9!
0:!
b0 ;!
b0 <!
0=!
b0 >!
b0 ?!
0@!
b10 A!
0$
0#
0"
0!
0%
#10000
0=
0&
#15000
1=
0>
1&
0'
b10 A!
#20000
0=
0&
#25000
1=
1&
b1010000010010000100000000111000001100000010100000100000000110000001000000001 +
b1 ,
b10 -
b11 .
b100 /
b101 0
b110 1
b111 2
b1000 3
b1001 4
b1010 5
b1001 6
b1010000010010000100000000111000001100000010100000100000000110000001000000001 7
b1010 8
b1010 9
b1010000010010000100000000111000001100000010100000100000000110000001000000001 :
b1001 ;
b0 6!
#30000
0=
0&
#35000
1=
1&
#36000
1(
b1010000010010000100000000111000001100000010100000100000000110000001000000001 )
1(!
1!!
1~
1u
1o
1m
1?
11!
1f
1e
1_
1^
1]
1T
1O
1L
1F
1D
#40000
0=
0&
#45000
1=
1&
b1000000100000001100000100000001010 4!
b10011010101111001 5!
b1010000010010000100000000111000001100000010100000100000000110000001000000001 6!
17!
#46000
0(
0?
#50000
0=
0&
#55000
1=
1&
07!
b1000000100000001010 8!
b1101111001 9!
1:!
#60000
0=
0&
#65000
1=
1&
0:!
b100000001010 ;!
b1111001 <!
1=!
#70000
0=
0&
#75000
1=
1&
0=!
b1010 >!
b1001 ?!
1@!
#80000
0=
0&
#85000
1=
1&
b1000000100000001100000100000001010000011000000111000010000000100100001010 +
b1010 ,
b1001 -
b1000 .
b111 /
b110 0
b101 1
b100 2
b11 3
b10 4
b1 5
b0 6
b1000000100000001100000100000001010000011000000111000010000000100100001010 7
b1010 8
b1000000100000001100000100000001010000011000000111000010000000100100001010 :
b0 ;
b1001 2!
13!
0@!
1$
1!
1%
#90000
0=
0&
#95000
1=
1&
03!
0%
#96000
1(
b1000000100000001100000100000001010000011000000111000010000000100100001010 )
1)!
0(!
1&!
0!!
0~
1|
1w
1v
0o
1n
1?
01!
10!
1.!
1g
0f
0_
0^
1W
1V
0T
0O
1N
0L
1G
0F
0D
#100000
0=
0&
#105000
1=
1&
b101000001000000001100000010000000010 4!
b10010001101000 5!
b1000000100000001100000100000001010000011000000111000010000000100100001010 6!
17!
#106000
0(
0?
#110000
0=
0&
#115000
1=
1&
07!
b10100000011000000010 8!
b1001000 9!
1:!
#120000
0=
0&
#125000
1=
1&
0:!
b101000000010 ;!
b1000 <!
1=!
#130000
0=
0&
#135000
1=
1&
0=!
b0 ?!
1@!
#140000
0=
0&
#145000
1=
1&
b1001000010000000011100000110000001010110001100000100000000110000001000000001 +
b1 ,
b10 -
b11 .
b100 /
b1100011 0
b110 2
b111 3
b1000 4
b1001 5
b100 6
b1001000010000000011100000110000001010110001100000100000000110000001000000001 7
b1010 8
b1100011 9
b1001000010000000011100000110000001010110001100000100000000110000001000000001 :
b100 ;
b0 2!
13!
0@!
0$
0!
1%
#150000
0=
0&
#155000
1=
1&
03!
0%
#156000
1(
b1001000010000000011100000110000001010110001100000100000000110000001000000001 )
0)!
1(!
0&!
1!!
1~
0|
0w
0v
1o
0m
1?
11!
00!
0.!
1j
1i
1^
1U
0N
1L
1D
#160000
0=
0&
#165000
1=
1&
b1000000100011000110000011100001001 4!
b10011010001111001 5!
b1001000010000000011100000110000001010110001100000100000000110000001000000001 6!
17!
#166000
0(
0?
#170000
0=
0&
#175000
1=
1&
07!
b1000110001100001001 8!
b1101001001 9!
1:!
#180000
0=
0&
#185000
1=
1&
0:!
b110001100001001 ;!
b1001001 <!
1=!
#190000
0=
0&
#195000
1=
1&
0=!
b1100011 >!
b100 ?!
1@!
#200000
0=
0&
#205000
1=
1&
b1111111000010010000100000000111000001100000010100000100000000110000001000000001 +
b101 0
b110 1
b111 2
b1000 3
b1001 4
b1111111 5
b1001 6
b1111111000010010000100000000111000001100000010100000100000000110000001000000001 7
b1010 8
b1111111 9
b1111111000010010000100000000111000001100000010100000100000000110000001000000001 :
b1001 ;
b100 2!
13!
0@!
1"
1%
#210000
0=
0&
#215000
1=
1&
03!
0%
#216000
1(
b1111111000010010000100000000111000001100000010100000100000000110000001000000001 )
0n
1m
1?
0j
0i
0g
1f
1_
0W
0V
0U
1T
1O
1F
1E
1C
1B
1A
#220000
0=
0&
#225000
1=
1&
b1000000100000001100000100001111111 4!
b10011010101111001 5!
b1111111000010010000100000000111000001100000010100000100000000110000001000000001 6!
17!
#226000
0(
0?
#230000
0=
0&
#235000
1=
1&
07!
b1000000100001111111 8!
b1101111001 9!
1:!
#240000
0=
0&
#245000
1=
1&
0:!
b100001111111 ;!
b1111001 <!
1=!
#250000
0=
0&
#255000
1=
1&
0=!
b1111111 >!
b1001 ?!
1@!
#260000
0=
0&
#265000
1=
1&
b1101000000010001001001100101100011010000110101100011000010011000000100100100 +
b100100 ,
b10000001 -
b1001 .
b1100011 /
b1101 0
b10001101 1
b1100101 2
b10010 3
b1 4
b1101 5
b101 6
b1101000000010001001001100101100011010000110101100011000010011000000100100100 7
b1010 8
b10001101 9
b1101000000010001001001100101100011010000110101100011000010011000000100100100 :
b101 ;
b1001 2!
13!
0@!
1$
0"
1!
1%
#270000
0=
0&
#275000
1=
1&
03!
0%
#276000
1(
b1101000000010001001001100101100011010000110101100011000010011000000100100100 )
1)!
0(!
1"!
0~
1|
1w
1v
0u
1r
1q
1?
01!
1/!
1,!
1l
1g
0f
1d
1`
0^
1Z
1Y
1V
0T
1S
0L
0F
0C
0B
0A
#280000
0=
0&
#285000
1=
1&
b1000000101100011100011010110010100001101 4!
b10011010101101001 5!
b1101000000010001001001100101100011010000110101100011000010011000000100100100 6!
17!
#286000
0(
0?
#290000
0=
0&
#295000
1=
1&
07!
b100000011000110100001101 8!
b101011001 9!
1:!
#300000
0=
0&
#305000
1=
1&
0:!
b1000110100001101 ;!
b1011001 <!
1=!
#310000
0=
0&
#315000
1=
1&
0=!
b10001101 >!
b101 ?!
1@!
#320000
0=
0&
#325000
1=
1&
b1110111111001011010101011000101110001101111100110001100111011010011110101110110 +
b1110110 ,
b111101 -
b11101101 .
b10001100 /
b11111001 0
b11000110 1
b11000101 2
b10101010 3
b11100101 4
b1110111 5
b100 6
b1110111111001011010101011000101110001101111100110001100111011010011110101110110 7
b1010 8
b11111001 9
b1110111111001011010101011000101110001101111100110001100111011010011110101110110 :
b100 ;
b101 2!
13!
0@!
1"
0!
1%
#330000
0=
0&
#335000
1=
1&
03!
0%
#336000
1(
b1110111111001011010101011000101110001101111100110001100111011010011110101110110 )
1'!
1&!
1%!
1$!
0"!
1}
1z
1y
1x
0w
0v
1u
1t
0r
0q
1p
0m
1?
10!
1-!
1+!
1k
1j
1i
1h
0g
1f
0d
1a
0Z
1X
1T
0S
1R
1P
1M
1J
1I
1H
1F
0D
1C
1B
1A
#340000
0=
0&
#345000
1=
1&
b111011011101101111110011100010111100101 4!
b10010001101000 5!
b1110111111001011010101011000101110001101111100110001100111011010011110101110110 6!
17!
#346000
0(
0?
#350000
0=
0&
#355000
1=
1&
07!
b111011011111100111100101 8!
b1001001000 9!
1:!
#360000
0=
0&
#365000
1=
1&
0:!
b1111100111100101 ;!
b1001000 <!
1=!
#370000
0=
0&
#375000
1=
1&
0=!
b11111001 >!
b100 ?!
1@!
#380000
0=
0&
#385000
1=
1&
b1100101001011011011110101011100110001011110100011001110111100101000111100010010 +
b10010 ,
b10001111 -
b11110010 .
b11001110 /
b11101000 0
b11000101 1
b1011100 2
b10111101 3
b101101 4
b1100101 5
b10 6
b1100101001011011011110101011100110001011110100011001110111100101000111100010010 7
b1010 8
b11110010 9
b1100101001011011011110101011100110001011110100011001110111100101000111100010010 :
b10 ;
b100 2!
13!
0@!
0$
1%
#390000
0=
0&
#395000
1=
1&
03!
0%
#396000
1(
b1100101001011011011110101011100110001011110100011001110111100101000111100010010 )
1(!
0%!
0$!
1"!
0!!
1~
0}
0|
1{
1v
1q
0o
1?
0/!
0,!
0+!
0k
1g
0f
0_
1\
1[
0X
1W
0V
1U
1S
1L
0I
0H
0F
0C
#400000
0=
0&
#405000
1=
1&
b1000111111110010111010001011110101100101 4!
b10010010001111001 5!
b1100101001011011011110101011100110001011110100011001110111100101000111100010010 6!
17!
#406000
0(
0?
#410000
0=
0&
#415000
1=
1&
07!
b111100101110100001100101 8!
b1001001001 9!
1:!
#420000
0=
0&
#425000
1=
1&
0:!
b1111001001100101 ;!
b101001 <!
1=!
#430000
0=
0&
#435000
1=
1&
0=!
b11110010 >!
b10 ?!
1@!
#440000
0=
0&
#445000
1=
1&
b1010011000011010001001110010110100111011010101000100000100000000000101001100011 +
b1100011 ,
b1010 -
b10000000 .
b100000 /
b10101010 0
b10011101 1
b10010110 2
b10011 3
b1101 4
b1010011 5
b100 6
b1010011000011010001001110010110100111011010101000100000100000000000101001100011 7
b1010 8
b10101010 9
b1010011000011010001001110010110100111011010101000100000100000000000101001100011 :
b100 ;
b10 2!
13!
0@!
1#
0"
1%
#450000
0=
0&
#455000
1=
1&
03!
0%
#456000
1(
b1010011000011010001001110010110100111011010101000100000100000000000101001100011 )
0)!
0'!
0"!
0~
0{
0z
0y
0v
0u
0t
1r
0q
0p
1n
1?
11!
0-!
1,!
1+!
0i
1d
1c
0a
1^
0\
0Y
1X
1V
0U
0T
0R
0P
0J
1F
0E
1C
0B
#460000
0=
0&
#465000
1=
1&
b110001110000000101010101001011001010011 4!
b10010001101001 5!
b1010011000011010001001110010110100111011010101000100000100000000000101001100011 6!
17!
#466000
0(
0?
#470000
0=
0&
#475000
1=
1&
07!
b100000001010101001010011 8!
1:!
#480000
0=
0&
#485000
1=
1&
0:!
b1010101001010011 ;!
b1001001 <!
1=!
#490000
0=
0&
#495000
1=
1&
0=!
b10101010 >!
b100 ?!
1@!
#500000
0=
0&
#505000
1=
1&
b111100110010100000101000100011110011110001110110101110000000101101010101101011 +
b1101011 ,
b11010101 -
b10 .
b10101110 /
b11101 0
b11001111 1
b100011 2
b1010 3
b11001010 4
b111100 5
b1 6
b111100110010100000101000100011110011110001110110101110000000101101010101101011 7
b1010 8
b11010101 9
b111100110010100000101000100011110011110001110110101110000000101101010101101011 :
b1 ;
b100 2!
13!
0@!
0#
1"
1%
#510000
0=
0&
#515000
1=
1&
03!
0%
#516000
1(
b111100110010100000101000100011110011110001110110101110000000101101010101101011 )
1)!
0(!
1'!
0&!
1%!
1#!
1"!
1~
0x
1v
1u
1t
1p
1o
0n
1m
1?
1.!
1k
0j
0h
1f
0c
1a
1_
0]
0[
1Z
0X
0W
1T
0S
0O
1N
0M
1I
1H
0G
0F
1E
1D
1B
0A
#520000
0=
0&
#525000
1=
1&
b1101010110101110110011110010001111001010 4!
b10011010101101000 5!
b111100110010100000101000100011110011110001110110101110000000101101010101101011 6!
17!
#526000
0(
0?
#530000
0=
0&
#535000
1=
1&
07!
b110101011100111111001010 8!
b101011000 9!
1:!
#540000
0=
0&
#545000
1=
1&
0:!
b1101010111001010 ;!
b11000 <!
1=!
#550000
0=
0&
#555000
1=
1&
0=!
b11010101 >!
b1 ?!
1@!
#560000
0=
0&
#565000
1=
1&
b10101110110001101011011011101011100010010111100011011000010000011000101011110010 +
b11110010 ,
b10001010 -
b1000001 .
b11011000 /
b1111000 0
b10001001 1
b11101011 2
b10110110 3
b11000110 4
b10101110 5
b0 6
b10101110110001101011011011101011100010010111100011011000010000011000101011110010 7
b1010 8
b11110010 9
b10101110110001101011011011101011100010010111100011011000010000011000101011110010 :
b0 ;
b1 2!
13!
0@!
1$
0"
1%
#570000
0=
0&
#575000
1=
1&
03!
0%
#576000
1(
b10101110110001101011011011101011100010010111100011011000010000011000101011110010 )
0)!
1(!
0'!
1&!
0%!
0#!
1!!
0~
1y
0v
0u
1s
0r
1q
0o
0m
1?
01!
0.!
1-!
1*!
1j
1i
0f
0e
0a
1\
1Y
1X
1U
0T
1S
1R
1P
1M
0L
1F
0C
1@
#580000
0=
0&
#585000
1=
1&
b1111001011011000100010011110101111000110 4!
b11010101101000 5!
b10101110110001101011011011101011100010010111100011011000010000011000101011110010 6!
17!
#586000
0(
0?
#590000
0=
0&
#595000
1=
1&
07!
b111100101110101111000110 8!
b1101000 9!
1:!
#600000
0=
0&
#605000
1=
1&
0:!
b1111001011000110 ;!
b1000 <!
1=!
#610000
0=
0&
#615000
1=
1&
0=!
b11110010 >!
b0 ?!
1@!
#620000
0=
0&
#625000
1=
1&
b10101011111100011101000111011010011111000010101110001000010110010101010111100 +
b10111100 ,
b101010 -
b1011 .
b1110001 /
b10000101 0
b1001111 1
b111011 2
b111010 3
b1111110 4
b10101 5
b10101011111100011101000111011010011111000010101110001000010110010101010111100 7
b1010 8
b10111100 9
b10101011111100011101000111011010011111000010101110001000010110010101010111100 :
b0 2!
13!
0@!
0$
1%
#630000
0=
0&
#635000
1=
1&
03!
0%
#636000
1(
b10101011111100011101000111011010011111000010101110001000010110010101010111100 )
1$!
0"!
1~
1|
0y
1w
0t
1r
0p
1o
1m
1?
00!
1/!
1.!
0+!
0l
0k
0j
0i
1h
1f
1e
1a
0`
1[
0Y
0X
0U
1T
0P
1L
1K
1J
0H
1G
0F
0D
1C
0B
0@
#640000
0=
0&
#645000
1=
1&
b1011110001110001100001010011101101111110 4!
b11010001101000 5!
b10101011111100011101000111011010011111000010101110001000010110010101010111100 6!
17!
#646000
0(
0?
#650000
0=
0&
#655000
1=
1&
07!
b101111001000010101111110 8!
b1001000 9!
1:!
#660000
0=
0&
#665000
1=
1&
0:!
b1011110001111110 ;!
1=!
#670000
0=
0&
#675000
1=
1&
0=!
b10111100 >!
1@!
#680000
0=
0&
#685000
1=
1&
b1011100100111111011011111111000100011111001111101001100011000101101100111110001 +
b11110001 ,
b11011001 -
b1100010 .
b1001100 /
b10011111 0
b10001111 1
b11111000 2
b10110111 3
b10011111 4
b1011100 5
b110 6
b1011100100111111011011111111000100011111001111101001100011000101101100111110001 7
b1010 8
b11111000 9
b1011100100111111011011111111000100011111001111101001100011000101101100111110001 :
b110 ;
13!
0@!
1%
#690000
0=
0&
#695000
1=
1&
03!
0%
#696000
1(
b1011100100111111011011111111000100011111001111101001100011000101101100111110001 )
1)!
0(!
1%!
0$!
1#!
1"!
0!!
0|
1z
1y
0w
1u
1t
0s
0r
1n
1?
11!
0/!
0.!
1+!
1l
1k
0a
1`
0_
0^
1Y
1X
1W
1U
0T
1P
1O
0J
0I
1H
0G
1D
1A
#700000
0=
0&
#705000
1=
1&
b1111000101100010100111111111100010011111 4!
b10010001101000 5!
b1011100100111111011011111111000100011111001111101001100011000101101100111110001 6!
17!
#706000
0(
0?
#710000
0=
0&
#715000
1=
1&
07!
b111100011111100010011111 8!
b1101000 9!
1:!
#720000
0=
0&
#725000
1=
1&
0:!
b1111100010011111 ;!
b1101000 <!
1=!
#730000
0=
0&
#735000
1=
1&
0=!
b11111000 >!
b110 ?!
1@!
#740000
0=
0&
