Verilog repository/Design Files/InputBuffer.v
`timescale 1ns / 1ps
//////////////////////////////////////////////////////////////////////////////////
// Company: University of Manchester
// Engineer: Lewis Hunton
// 
// Create Date:    00:15:17 02/27/2026 
// Design Name: 
// Module Name:    InputBuffer 
// Project Name: FPGA Implementation of a MLP Artificial Neural Network Optimised for Size
// Target Devices: XC3S1500 Spartan-3
// Tool versions: Xilinx 14.2
// Description: Input Buffer
//
// Dependencies: 
//
// Revision: 
// Revision 0.01 - File Created
// Additional Comments: 
//
//////////////////////////////////////////////////////////////////////////////////
module InputBuffer #(
	parameter W = 4,
	parameter N = 64,
	parameter DoubleBuffer = 0
)(
	input wire Clk,
	input wire Reset,
	
	//Host write controls (python stuff)
	input wire WriteValid,
	input wire [W-1:0] WriteData,
	output wire WriteReady,
	input wire Commit,
	
	output reg BufferFull,
	
	
	//MAC read side (on fpga)
	input wire ReadEnable,
	input wire [5:0] ReadAddress,
	output reg [W-1:0] ReadData,
	
	output reg [5:0] WriteIndex
    );
	 
	 reg [5:0] WriteCount;
	 reg Loaded;
	 
	 reg [W-1:0] Memory [0:N-1];
	 
	 reg WriteACK;
	 
	 assign WriteReady = WriteACK;
	 
	 integer i;
	 always @ (posedge Clk) begin
		if (Reset) begin
			WriteCount <= 6'd0;
			Loaded <= 1'b0;
			BufferFull <= 1'b0;
			WriteIndex <= 0;
			WriteACK <= 0;
		end else begin
			WriteACK <= 0;
		
			if (WriteValid && !BufferFull) begin
				Memory[WriteIndex] <= WriteData;
				WriteIndex <= WriteIndex + 6'd1;
				
				WriteACK <= 1;
				
				if (WriteIndex == N-1)
					Loaded <= 1'b1;
			end
			if (Commit && Loaded) begin
				BufferFull <= 1'b1;
			end
			//Clears flags when compute side consumes
			//external logic should clear via reset
		end
	end
			
	always @ (posedge Clk) begin
		if(ReadEnable) begin
			ReadData <= Memory[ReadAddress];
		end
	end

endmodule

Verilog repository/Test Benches/InputBuffer_tb.v
`timescale 1ns / 1ps

////////////////////////////////////////////////////////////////////////////////
// Company: University of Manchester
// Engineer: Lewis Hunton
//
// Create Date:   01:54:37 04/14/2026
// Design Name:   InputBuffer
// Module Name:   /home/ise/CompleteNeuralNetworkV2/InputBuffer_tb.v
// Project Name:  FPGA Implementation of a MLP Artificial Neural Network Optimised for Size
// Target Device:  XC3S1500 Spartan-3
// Tool versions:  Xilinx 14.2
// Description: Input Buffer Test Bench
//
// Verilog Test Fixture created by ISE for module: InputBuffer
//
// Dependencies:
// 
// Revision:
// Revision 0.01 - File Created
// Additional Comments:
// 
////////////////////////////////////////////////////////////////////////////////

module InputBuffer_tb;

	// Inputs
	reg Clk;
	reg Reset;
	reg WriteValid;
	reg [3:0] WriteData;
	reg Commit;
	reg ReadEnable;
	reg [5:0] ReadAddress;

	// Outputs
	wire WriteReady;
	wire BufferFull;
	wire [3:0] ReadData;
	wire [5:0] WriteIndex;

	// Instantiate the Unit Under Test (UUT)
	InputBuffer uut (
		.Clk(Clk), 
		.Reset(Reset), 
		.WriteValid(WriteValid), 
		.WriteData(WriteData), 
		.WriteReady(WriteReady), 
		.Commit(Commit), 
		.BufferFull(BufferFull), 
		.ReadEnable(ReadEnable), 
		.ReadAddress(ReadAddress), 
		.ReadData(ReadData), 
		.WriteIndex(WriteIndex)
	);
	
	initial begin
		Clk = 0;
		forever #5 Clk = ~Clk;
	end
	
	integer Failed;
	integer i;
	
	task WriteWord;
		input [3:0] Data;
		begin
			@(posedge Clk);
			#1;
			WriteValid = 1;
			WriteData = Data;
			@(posedge Clk);
			#1;
			if(!WriteReady) begin
				$display("FAIL: WriteReady not asserted for Data=%0d", Data);
				Failed = Failed + 1;
			end
			WriteValid = 0;
		end
	endtask
	
	task FillBuffer;
		begin
			for (i = 0; i < 64; i = i + 1) begin
				@(posedge Clk); 
				#1;
				WriteValid = 1;
				WriteData = i[3:0];
			end
			@(posedge Clk); 
			#1;
			WriteValid = 0;
		end
	endtask
	
	task CommitAndWait;
		begin
			@(posedge Clk);
			#1;
			Commit = 1;
			@(posedge Clk);
			#1;
			Commit = 0;
			
			if(!BufferFull) begin
				$display("FAIL: BufferFull not asserted after commit");
				Failed = Failed + 1;
			end else begin
				$display("PASS: BufferFUll Asserted after Commit");
			end
		end
	endtask
	
	task VerifyReadback;
		reg [3:0] Expected;
		begin
			for (i = 0; i < 64; i = i + 1) begin
				@(posedge Clk);
				#1;
				ReadEnable = 1;
				ReadAddress = i[5:0];
				@(posedge Clk);
				#1;
				ReadEnable = 0;
				
				Expected = i[3:0];
				if(ReadData !== Expected) begin
					$display("FAIL (readback): Addr=%0d Expected=%0d Output=%0d", i, Expected, ReadData);
					Failed = Failed + 1;
				end else begin
					$display("PASS (readback): Addr=%0d Data=%0d", i, ReadData);
				end
			end
		end
	endtask
	
	initial begin
		Failed = 0;
		Reset = 1;
		WriteValid = 0;
		WriteData = 0;
		Commit = 0;
		ReadEnable = 0;
		ReadAddress = 0;
		
		$dumpfile("InputBuffer_tb.vcd");
		$dumpvars(0, InputBuffer_tb);
		
		@(posedge Clk);
		#1;
		@(posedge Clk);
		#1;
		Reset = 0;
		@(posedge Clk);
		#1;
		
		$display("Test 1: Fill and readback");
		FillBuffer;
		CommitAndWait;
		VerifyReadback;
		
		$display("Test 2: No write when bufferfull");
		@(posedge Clk);
		#1;
		WriteValid = 1;
		WriteData = 4'hF;
		@(posedge Clk);
		#1;
		if(WriteReady) begin
			$display("FAIL: WriteReady asserted when bufferfull - should be blocked");
			Failed = Failed + 1;
		end else begin
			$display("PASS: Write correctly blocked when BufferFull");
		end
		WriteValid = 0;
		
		$display("Test 3: Reset");
		@(posedge Clk);
		#1;
		Reset = 1;
		@(posedge Clk);
		#1;
		@(posedge Clk);
		#1;
		Reset = 0;
		@(posedge Clk);
		#1;
		
		
		if(BufferFull) begin
			$display("FAIL: BufferFull not cleared after Reset");
			Failed = Failed + 1;
		end else begin
			$display("PASS: BufferFUll cleared after Reset");
		end
		
		if(WriteIndex !== 0) begin
			$display("FAIL: WriteIndex not cleared after Reset, output=%0d", WriteIndex);
			Failed = Failed + 1;
		end else begin
			$display("PASS: WriteIndex cleared after Reset");
		end
		
		$display("Test 4: Partial write then commit");
		for(i = 0; i < 4; i = i + 1)
			WriteWord(i[3:0]);
			
		@(posedge Clk);
		#1;
		Commit = 1;
		@(posedge Clk);
		#1;
		Commit = 0;
		
		if(BufferFull) begin
			$display("FAIL: Bufferfull set after partial write");
			Failed = Failed + 1;
		end else begin
			$display("PASS: Bufferfull not set after partial write");
		end
		
		$display("Test 5: Complete fill after partial");
		for(i = 4; i < 64; i = i + 1)
			WriteWord(i[3:0]);
		CommitAndWait;
		
		if(Failed == 0)
			$display("ALL inputbuffer tests passed");
		else 
			$display("FAILED: %0d tests failed", Failed);
		
		$finish;
	end
	
endmodule

Verilog repository/Test Benches/Test Bench Results/InputBuffer_tb.vcd
$date
   Tue Apr 14 03:36:37 2026
$end
$version
  P.20131013
$end
$timescale
  1ps
$end
$scope module InputBuffer_tb $end
$var wire 1 ? WriteReady $end
$var wire 1 " BufferFull $end
$var wire 1 # ReadData [3] $end
$var wire 1 $ ReadData [2] $end
$var wire 1 % ReadData [1] $end
$var wire 1 & ReadData [0] $end
$var wire 1 ' WriteIndex [5] $end
$var wire 1 ( WriteIndex [4] $end
$var wire 1 ) WriteIndex [3] $end
$var wire 1 * WriteIndex [2] $end
$var wire 1 + WriteIndex [1] $end
$var wire 1 , WriteIndex [0] $end
$var reg 1 - Clk $end
$var reg 1 . Reset $end
$var reg 1 / WriteValid $end
$var reg 4 0 WriteData [3:0] $end
$var reg 1 1 Commit $end
$var reg 1 2 ReadEnable $end
$var reg 6 3 ReadAddress [5:0] $end
$var integer 32 4 Failed $end
$var integer 32 5 i $end
$scope task WriteWord $end
$var reg 4 6 Data [3:0] $end
$upscope $end
$scope task FillBuffer $end
$upscope $end
$scope task CommitAndWait $end
$upscope $end
$scope task VerifyReadback $end
$var reg 4 7 Expected [3:0] $end
$upscope $end
$scope module uut $end
$var wire 1 8 Clk $end
$var wire 1 9 Reset $end
$var wire 1 : WriteValid $end
$var wire 1 ; WriteData [3] $end
$var wire 1 < WriteData [2] $end
$var wire 1 = WriteData [1] $end
$var wire 1 > WriteData [0] $end
$var wire 1 ? WriteReady $end
$var wire 1 @ Commit $end
$var wire 1 A ReadEnable $end
$var wire 1 B ReadAddress [5] $end
$var wire 1 C ReadAddress [4] $end
$var wire 1 D ReadAddress [3] $end
$var wire 1 E ReadAddress [2] $end
$var wire 1 F ReadAddress [1] $end
$var wire 1 G ReadAddress [0] $end
$var reg 1 H BufferFull $end
$var reg 4 I ReadData [3:0] $end
$var reg 6 J WriteIndex [5:0] $end
$var reg 6 K WriteCount [5:0] $end
$var reg 1 L Loaded $end
$var reg 256 M Memory [3:0] $end
$var reg 1 N WriteACK $end
$var integer 32 O i $end
$upscope $end
$upscope $end
$enddefinitions $end
#0
$dumpvars
0-
1.
0/
b0 0
01
02
b0 3
b0 4
bx 5
bx 6
bx 7
x&
x%
x$
x#
x,
x+
x*
x)
x(
x'
xH
bx I
bx J
bx K
xL
bx M
xN
bx O
08
x?
x"
0:
0>
0=
0<
0;
0@
0A
0G
0F
0E
0D
0C
0B
19
$end
#5000
1-
0,
0+
0*
0)
0(
0'
0H
b0 J
b0 K
0L
0N
18
0?
0"
#10000
0-
08
#15000
1-
18
#16000
0.
09
#20000
0-
08
#25000
1-
18
#26000
b0 5
#30000
0-
08
#35000
1-
18
#36000
1/
b1 5
1:
#40000
0-
08
#45000
1-
1,
b1 J
b0xxxxxxxxxxxxxxxxxxxxxxxxxxxxxxxxxxxxxxxxxxxxxxxxxxxxxxxxxxxxxxxxxxxxxxxxxxxxxxxxxxxxxxxxxxxxxxxxxxxxxxxxxxxxxxxxxxxxxxxxxxxxxxxxxxxxxxxxxxxxxxxxxxxxxxxxxxxxxxxxxxxxxxxxxxxxxxxxxxxxxxxxxxxxxxxxxxxxxxxxxxxxxxxxxxxxxxxxxxxxxxxxxxxxxxxxxxxxxxxxxxxxxxxxxxxx M
1N
18
1?
#46000
b1 0
b10 5
1>
#50000
0-
08
#55000
1-
0,
1+
b10 J
b1xxxxxxxxxxxxxxxxxxxxxxxxxxxxxxxxxxxxxxxxxxxxxxxxxxxxxxxxxxxxxxxxxxxxxxxxxxxxxxxxxxxxxxxxxxxxxxxxxxxxxxxxxxxxxxxxxxxxxxxxxxxxxxxxxxxxxxxxxxxxxxxxxxxxxxxxxxxxxxxxxxxxxxxxxxxxxxxxxxxxxxxxxxxxxxxxxxxxxxxxxxxxxxxxxxxxxxxxxxxxxxxxxxxxxxxxxxxxxxxxxxxxxxxx M
1N
18
#56000
b10 0
b11 5
0>
1=
#60000
0-
08
#65000
1-
1,
b11 J
b10010xxxxxxxxxxxxxxxxxxxxxxxxxxxxxxxxxxxxxxxxxxxxxxxxxxxxxxxxxxxxxxxxxxxxxxxxxxxxxxxxxxxxxxxxxxxxxxxxxxxxxxxxxxxxxxxxxxxxxxxxxxxxxxxxxxxxxxxxxxxxxxxxxxxxxxxxxxxxxxxxxxxxxxxxxxxxxxxxxxxxxxxxxxxxxxxxxxxxxxxxxxxxxxxxxxxxxxxxxxxxxxxxxxxxxxxxxxxxxxxxxxxx M
1N
18
#66000
b11 0
b100 5
1>
#70000
0-
08
#75000
1-
0,
0+
1*
b100 J
b100100011xxxxxxxxxxxxxxxxxxxxxxxxxxxxxxxxxxxxxxxxxxxxxxxxxxxxxxxxxxxxxxxxxxxxxxxxxxxxxxxxxxxxxxxxxxxxxxxxxxxxxxxxxxxxxxxxxxxxxxxxxxxxxxxxxxxxxxxxxxxxxxxxxxxxxxxxxxxxxxxxxxxxxxxxxxxxxxxxxxxxxxxxxxxxxxxxxxxxxxxxxxxxxxxxxxxxxxxxxxxxxxxxxxxxxxxxxxxxxxxx M
1N
18
#76000
b100 0
b101 5
0>
0=
1<
#80000
0-
08
#85000
1-
1,
b101 J
b1001000110100xxxxxxxxxxxxxxxxxxxxxxxxxxxxxxxxxxxxxxxxxxxxxxxxxxxxxxxxxxxxxxxxxxxxxxxxxxxxxxxxxxxxxxxxxxxxxxxxxxxxxxxxxxxxxxxxxxxxxxxxxxxxxxxxxxxxxxxxxxxxxxxxxxxxxxxxxxxxxxxxxxxxxxxxxxxxxxxxxxxxxxxxxxxxxxxxxxxxxxxxxxxxxxxxxxxxxxxxxxxxxxxxxxxxxxxxxxxx M
1N
18
#86000
b101 0
b110 5
1>
#90000
0-
08
#95000
1-
0,
1+
b110 J
b10010001101000101xxxxxxxxxxxxxxxxxxxxxxxxxxxxxxxxxxxxxxxxxxxxxxxxxxxxxxxxxxxxxxxxxxxxxxxxxxxxxxxxxxxxxxxxxxxxxxxxxxxxxxxxxxxxxxxxxxxxxxxxxxxxxxxxxxxxxxxxxxxxxxxxxxxxxxxxxxxxxxxxxxxxxxxxxxxxxxxxxxxxxxxxxxxxxxxxxxxxxxxxxxxxxxxxxxxxxxxxxxxxxxxxxxxxxxxx M
1N
18
#96000
b110 0
b111 5
0>
1=
#100000
0-
08
#105000
1-
1,
b111 J
b100100011010001010110xxxxxxxxxxxxxxxxxxxxxxxxxxxxxxxxxxxxxxxxxxxxxxxxxxxxxxxxxxxxxxxxxxxxxxxxxxxxxxxxxxxxxxxxxxxxxxxxxxxxxxxxxxxxxxxxxxxxxxxxxxxxxxxxxxxxxxxxxxxxxxxxxxxxxxxxxxxxxxxxxxxxxxxxxxxxxxxxxxxxxxxxxxxxxxxxxxxxxxxxxxxxxxxxxxxxxxxxxxxxxxxxxxxx M
1N
18
#106000
b111 0
b1000 5
1>
#110000
0-
08
#115000
1-
0,
0+
0*
1)
b1000 J
b1001000110100010101100111xxxxxxxxxxxxxxxxxxxxxxxxxxxxxxxxxxxxxxxxxxxxxxxxxxxxxxxxxxxxxxxxxxxxxxxxxxxxxxxxxxxxxxxxxxxxxxxxxxxxxxxxxxxxxxxxxxxxxxxxxxxxxxxxxxxxxxxxxxxxxxxxxxxxxxxxxxxxxxxxxxxxxxxxxxxxxxxxxxxxxxxxxxxxxxxxxxxxxxxxxxxxxxxxxxxxxxxxxxxxxxxx M
1N
18
#116000
b1000 0
b1001 5
0>
0=
0<
1;
#120000
0-
08
#125000
1-
1,
b1001 J
b10010001101000101011001111000xxxxxxxxxxxxxxxxxxxxxxxxxxxxxxxxxxxxxxxxxxxxxxxxxxxxxxxxxxxxxxxxxxxxxxxxxxxxxxxxxxxxxxxxxxxxxxxxxxxxxxxxxxxxxxxxxxxxxxxxxxxxxxxxxxxxxxxxxxxxxxxxxxxxxxxxxxxxxxxxxxxxxxxxxxxxxxxxxxxxxxxxxxxxxxxxxxxxxxxxxxxxxxxxxxxxxxxxxxxx M
1N
18
#126000
b1001 0
b1010 5
1>
#130000
0-
08
#135000
1-
0,
1+
b1010 J
b100100011010001010110011110001001xxxxxxxxxxxxxxxxxxxxxxxxxxxxxxxxxxxxxxxxxxxxxxxxxxxxxxxxxxxxxxxxxxxxxxxxxxxxxxxxxxxxxxxxxxxxxxxxxxxxxxxxxxxxxxxxxxxxxxxxxxxxxxxxxxxxxxxxxxxxxxxxxxxxxxxxxxxxxxxxxxxxxxxxxxxxxxxxxxxxxxxxxxxxxxxxxxxxxxxxxxxxxxxxxxxxxxxx M
1N
18
#136000
b1010 0
b1011 5
0>
1=
#140000
0-
08
#145000
1-
1,
b1011 J
b1001000110100010101100111100010011010xxxxxxxxxxxxxxxxxxxxxxxxxxxxxxxxxxxxxxxxxxxxxxxxxxxxxxxxxxxxxxxxxxxxxxxxxxxxxxxxxxxxxxxxxxxxxxxxxxxxxxxxxxxxxxxxxxxxxxxxxxxxxxxxxxxxxxxxxxxxxxxxxxxxxxxxxxxxxxxxxxxxxxxxxxxxxxxxxxxxxxxxxxxxxxxxxxxxxxxxxxxxxxxxxxxx M
1N
18
#146000
b1011 0
b1100 5
1>
#150000
0-
08
#155000
1-
0,
0+
1*
b1100 J
b10010001101000101011001111000100110101011xxxxxxxxxxxxxxxxxxxxxxxxxxxxxxxxxxxxxxxxxxxxxxxxxxxxxxxxxxxxxxxxxxxxxxxxxxxxxxxxxxxxxxxxxxxxxxxxxxxxxxxxxxxxxxxxxxxxxxxxxxxxxxxxxxxxxxxxxxxxxxxxxxxxxxxxxxxxxxxxxxxxxxxxxxxxxxxxxxxxxxxxxxxxxxxxxxxxxxxxxxxxxxxx M
1N
18
#156000
b1100 0
b1101 5
0>
0=
1<
#160000
0-
08
#165000
1-
1,
b1101 J
b100100011010001010110011110001001101010111100xxxxxxxxxxxxxxxxxxxxxxxxxxxxxxxxxxxxxxxxxxxxxxxxxxxxxxxxxxxxxxxxxxxxxxxxxxxxxxxxxxxxxxxxxxxxxxxxxxxxxxxxxxxxxxxxxxxxxxxxxxxxxxxxxxxxxxxxxxxxxxxxxxxxxxxxxxxxxxxxxxxxxxxxxxxxxxxxxxxxxxxxxxxxxxxxxxxxxxxxxxxx M
1N
18
#166000
b1101 0
b1110 5
1>
#170000
0-
08
#175000
1-
0,
1+
b1110 J
b1001000110100010101100111100010011010101111001101xxxxxxxxxxxxxxxxxxxxxxxxxxxxxxxxxxxxxxxxxxxxxxxxxxxxxxxxxxxxxxxxxxxxxxxxxxxxxxxxxxxxxxxxxxxxxxxxxxxxxxxxxxxxxxxxxxxxxxxxxxxxxxxxxxxxxxxxxxxxxxxxxxxxxxxxxxxxxxxxxxxxxxxxxxxxxxxxxxxxxxxxxxxxxxxxxxxxxxxx M
1N
18
#176000
b1110 0
b1111 5
0>
1=
#180000
0-
08
#185000
1-
1,
b1111 J
b10010001101000101011001111000100110101011110011011110xxxxxxxxxxxxxxxxxxxxxxxxxxxxxxxxxxxxxxxxxxxxxxxxxxxxxxxxxxxxxxxxxxxxxxxxxxxxxxxxxxxxxxxxxxxxxxxxxxxxxxxxxxxxxxxxxxxxxxxxxxxxxxxxxxxxxxxxxxxxxxxxxxxxxxxxxxxxxxxxxxxxxxxxxxxxxxxxxxxxxxxxxxxxxxxxxxxx M
1N
18
#186000
b1111 0
b10000 5
1>
#190000
0-
08
#195000
1-
0,
0+
0*
0)
1(
b10000 J
b100100011010001010110011110001001101010111100110111101111xxxxxxxxxxxxxxxxxxxxxxxxxxxxxxxxxxxxxxxxxxxxxxxxxxxxxxxxxxxxxxxxxxxxxxxxxxxxxxxxxxxxxxxxxxxxxxxxxxxxxxxxxxxxxxxxxxxxxxxxxxxxxxxxxxxxxxxxxxxxxxxxxxxxxxxxxxxxxxxxxxxxxxxxxxxxxxxxxxxxxxxxxxxxxxxx M
1N
18
#196000
b0 0
b10001 5
0>
0=
0<
0;
#200000
0-
08
#205000
1-
1,
b10001 J
b1001000110100010101100111100010011010101111001101111011110000xxxxxxxxxxxxxxxxxxxxxxxxxxxxxxxxxxxxxxxxxxxxxxxxxxxxxxxxxxxxxxxxxxxxxxxxxxxxxxxxxxxxxxxxxxxxxxxxxxxxxxxxxxxxxxxxxxxxxxxxxxxxxxxxxxxxxxxxxxxxxxxxxxxxxxxxxxxxxxxxxxxxxxxxxxxxxxxxxxxxxxxxxxxx M
1N
18
#206000
b1 0
b10010 5
1>
#210000
0-
08
#215000
1-
0,
1+
b10010 J
b10010001101000101011001111000100110101011110011011110111100000001xxxxxxxxxxxxxxxxxxxxxxxxxxxxxxxxxxxxxxxxxxxxxxxxxxxxxxxxxxxxxxxxxxxxxxxxxxxxxxxxxxxxxxxxxxxxxxxxxxxxxxxxxxxxxxxxxxxxxxxxxxxxxxxxxxxxxxxxxxxxxxxxxxxxxxxxxxxxxxxxxxxxxxxxxxxxxxxxxxxxxxxx M
1N
18
#216000
b10 0
b10011 5
0>
1=
#220000
0-
08
#225000
1-
1,
b10011 J
b100100011010001010110011110001001101010111100110111101111000000010010xxxxxxxxxxxxxxxxxxxxxxxxxxxxxxxxxxxxxxxxxxxxxxxxxxxxxxxxxxxxxxxxxxxxxxxxxxxxxxxxxxxxxxxxxxxxxxxxxxxxxxxxxxxxxxxxxxxxxxxxxxxxxxxxxxxxxxxxxxxxxxxxxxxxxxxxxxxxxxxxxxxxxxxxxxxxxxxxxxxx M
1N
18
#226000
b11 0
b10100 5
1>
#230000
0-
08
#235000
1-
0,
0+
1*
b10100 J
b1001000110100010101100111100010011010101111001101111011110000000100100011xxxxxxxxxxxxxxxxxxxxxxxxxxxxxxxxxxxxxxxxxxxxxxxxxxxxxxxxxxxxxxxxxxxxxxxxxxxxxxxxxxxxxxxxxxxxxxxxxxxxxxxxxxxxxxxxxxxxxxxxxxxxxxxxxxxxxxxxxxxxxxxxxxxxxxxxxxxxxxxxxxxxxxxxxxxxxxxx M
1N
18
#236000
b100 0
b10101 5
0>
0=
1<
#240000
0-
08
#245000
1-
1,
b10101 J
b10010001101000101011001111000100110101011110011011110111100000001001000110100xxxxxxxxxxxxxxxxxxxxxxxxxxxxxxxxxxxxxxxxxxxxxxxxxxxxxxxxxxxxxxxxxxxxxxxxxxxxxxxxxxxxxxxxxxxxxxxxxxxxxxxxxxxxxxxxxxxxxxxxxxxxxxxxxxxxxxxxxxxxxxxxxxxxxxxxxxxxxxxxxxxxxxxxxxxx M
1N
18
#246000
b101 0
b10110 5
1>
#250000
0-
08
#255000
1-
0,
1+
b10110 J
b100100011010001010110011110001001101010111100110111101111000000010010001101000101xxxxxxxxxxxxxxxxxxxxxxxxxxxxxxxxxxxxxxxxxxxxxxxxxxxxxxxxxxxxxxxxxxxxxxxxxxxxxxxxxxxxxxxxxxxxxxxxxxxxxxxxxxxxxxxxxxxxxxxxxxxxxxxxxxxxxxxxxxxxxxxxxxxxxxxxxxxxxxxxxxxxxxxx M
1N
18
#256000
b110 0
b10111 5
0>
1=
#260000
0-
08
#265000
1-
1,
b10111 J
b1001000110100010101100111100010011010101111001101111011110000000100100011010001010110xxxxxxxxxxxxxxxxxxxxxxxxxxxxxxxxxxxxxxxxxxxxxxxxxxxxxxxxxxxxxxxxxxxxxxxxxxxxxxxxxxxxxxxxxxxxxxxxxxxxxxxxxxxxxxxxxxxxxxxxxxxxxxxxxxxxxxxxxxxxxxxxxxxxxxxxxxxxxxxxxxxx M
1N
18
#266000
b111 0
b11000 5
1>
#270000
0-
08
#275000
1-
0,
0+
0*
1)
b11000 J
b10010001101000101011001111000100110101011110011011110111100000001001000110100010101100111xxxxxxxxxxxxxxxxxxxxxxxxxxxxxxxxxxxxxxxxxxxxxxxxxxxxxxxxxxxxxxxxxxxxxxxxxxxxxxxxxxxxxxxxxxxxxxxxxxxxxxxxxxxxxxxxxxxxxxxxxxxxxxxxxxxxxxxxxxxxxxxxxxxxxxxxxxxxxxxx M
1N
18
#276000
b1000 0
b11001 5
0>
0=
0<
1;
#280000
0-
08
#285000
1-
1,
b11001 J
b100100011010001010110011110001001101010111100110111101111000000010010001101000101011001111000xxxxxxxxxxxxxxxxxxxxxxxxxxxxxxxxxxxxxxxxxxxxxxxxxxxxxxxxxxxxxxxxxxxxxxxxxxxxxxxxxxxxxxxxxxxxxxxxxxxxxxxxxxxxxxxxxxxxxxxxxxxxxxxxxxxxxxxxxxxxxxxxxxxxxxxxxxxx M
1N
18
#286000
b1001 0
b11010 5
1>
#290000
0-
08
#295000
1-
0,
1+
b11010 J
b1001000110100010101100111100010011010101111001101111011110000000100100011010001010110011110001001xxxxxxxxxxxxxxxxxxxxxxxxxxxxxxxxxxxxxxxxxxxxxxxxxxxxxxxxxxxxxxxxxxxxxxxxxxxxxxxxxxxxxxxxxxxxxxxxxxxxxxxxxxxxxxxxxxxxxxxxxxxxxxxxxxxxxxxxxxxxxxxxxxxxxxxx M
1N
18
#296000
b1010 0
b11011 5
0>
1=
#300000
0-
08
#305000
1-
1,
b11011 J
b10010001101000101011001111000100110101011110011011110111100000001001000110100010101100111100010011010xxxxxxxxxxxxxxxxxxxxxxxxxxxxxxxxxxxxxxxxxxxxxxxxxxxxxxxxxxxxxxxxxxxxxxxxxxxxxxxxxxxxxxxxxxxxxxxxxxxxxxxxxxxxxxxxxxxxxxxxxxxxxxxxxxxxxxxxxxxxxxxxxxxx M
1N
18
#306000
b1011 0
b11100 5
1>
#310000
0-
08
#315000
1-
0,
0+
1*
b11100 J
b100100011010001010110011110001001101010111100110111101111000000010010001101000101011001111000100110101011xxxxxxxxxxxxxxxxxxxxxxxxxxxxxxxxxxxxxxxxxxxxxxxxxxxxxxxxxxxxxxxxxxxxxxxxxxxxxxxxxxxxxxxxxxxxxxxxxxxxxxxxxxxxxxxxxxxxxxxxxxxxxxxxxxxxxxxxxxxxxxxx M
1N
18
#316000
b1100 0
b11101 5
0>
0=
1<
#320000
0-
08
#325000
1-
1,
b11101 J
b1001000110100010101100111100010011010101111001101111011110000000100100011010001010110011110001001101010111100xxxxxxxxxxxxxxxxxxxxxxxxxxxxxxxxxxxxxxxxxxxxxxxxxxxxxxxxxxxxxxxxxxxxxxxxxxxxxxxxxxxxxxxxxxxxxxxxxxxxxxxxxxxxxxxxxxxxxxxxxxxxxxxxxxxxxxxxxxxx M
1N
18
#326000
b1101 0
b11110 5
1>
#330000
0-
08
#335000
1-
0,
1+
b11110 J
b10010001101000101011001111000100110101011110011011110111100000001001000110100010101100111100010011010101111001101xxxxxxxxxxxxxxxxxxxxxxxxxxxxxxxxxxxxxxxxxxxxxxxxxxxxxxxxxxxxxxxxxxxxxxxxxxxxxxxxxxxxxxxxxxxxxxxxxxxxxxxxxxxxxxxxxxxxxxxxxxxxxxxxxxxxxxxx M
1N
18
#336000
b1110 0
b11111 5
0>
1=
#340000
0-
08
#345000
1-
1,
b11111 J
b100100011010001010110011110001001101010111100110111101111000000010010001101000101011001111000100110101011110011011110xxxxxxxxxxxxxxxxxxxxxxxxxxxxxxxxxxxxxxxxxxxxxxxxxxxxxxxxxxxxxxxxxxxxxxxxxxxxxxxxxxxxxxxxxxxxxxxxxxxxxxxxxxxxxxxxxxxxxxxxxxxxxxxxxxxx M
1N
18
#346000
b1111 0
b100000 5
1>
#350000
0-
08
#355000
1-
0,
0+
0*
0)
0(
1'
b100000 J
b1001000110100010101100111100010011010101111001101111011110000000100100011010001010110011110001001101010111100110111101111xxxxxxxxxxxxxxxxxxxxxxxxxxxxxxxxxxxxxxxxxxxxxxxxxxxxxxxxxxxxxxxxxxxxxxxxxxxxxxxxxxxxxxxxxxxxxxxxxxxxxxxxxxxxxxxxxxxxxxxxxxxxxxxx M
1N
18
#356000
b0 0
b100001 5
0>
0=
0<
0;
#360000
0-
08
#365000
1-
1,
b100001 J
b10010001101000101011001111000100110101011110011011110111100000001001000110100010101100111100010011010101111001101111011110000xxxxxxxxxxxxxxxxxxxxxxxxxxxxxxxxxxxxxxxxxxxxxxxxxxxxxxxxxxxxxxxxxxxxxxxxxxxxxxxxxxxxxxxxxxxxxxxxxxxxxxxxxxxxxxxxxxxxxxxxxxxx M
1N
18
#366000
b1 0
b100010 5
1>
#370000
0-
08
#375000
1-
0,
1+
b100010 J
b100100011010001010110011110001001101010111100110111101111000000010010001101000101011001111000100110101011110011011110111100000001xxxxxxxxxxxxxxxxxxxxxxxxxxxxxxxxxxxxxxxxxxxxxxxxxxxxxxxxxxxxxxxxxxxxxxxxxxxxxxxxxxxxxxxxxxxxxxxxxxxxxxxxxxxxxxxxxxxxxxxx M
1N
18
#376000
b10 0
b100011 5
0>
1=
#380000
0-
08
#385000
1-
1,
b100011 J
b1001000110100010101100111100010011010101111001101111011110000000100100011010001010110011110001001101010111100110111101111000000010010xxxxxxxxxxxxxxxxxxxxxxxxxxxxxxxxxxxxxxxxxxxxxxxxxxxxxxxxxxxxxxxxxxxxxxxxxxxxxxxxxxxxxxxxxxxxxxxxxxxxxxxxxxxxxxxxxxxx M
1N
18
#386000
b11 0
b100100 5
1>
#390000
0-
08
#395000
1-
0,
0+
1*
b100100 J
b10010001101000101011001111000100110101011110011011110111100000001001000110100010101100111100010011010101111001101111011110000000100100011xxxxxxxxxxxxxxxxxxxxxxxxxxxxxxxxxxxxxxxxxxxxxxxxxxxxxxxxxxxxxxxxxxxxxxxxxxxxxxxxxxxxxxxxxxxxxxxxxxxxxxxxxxxxxxxx M
1N
18
#396000
b100 0
b100101 5
0>
0=
1<
#400000
0-
08
#405000
1-
1,
b100101 J
b100100011010001010110011110001001101010111100110111101111000000010010001101000101011001111000100110101011110011011110111100000001001000110100xxxxxxxxxxxxxxxxxxxxxxxxxxxxxxxxxxxxxxxxxxxxxxxxxxxxxxxxxxxxxxxxxxxxxxxxxxxxxxxxxxxxxxxxxxxxxxxxxxxxxxxxxxxx M
1N
18
#406000
b101 0
b100110 5
1>
#410000
0-
08
#415000
1-
0,
1+
b100110 J
b1001000110100010101100111100010011010101111001101111011110000000100100011010001010110011110001001101010111100110111101111000000010010001101000101xxxxxxxxxxxxxxxxxxxxxxxxxxxxxxxxxxxxxxxxxxxxxxxxxxxxxxxxxxxxxxxxxxxxxxxxxxxxxxxxxxxxxxxxxxxxxxxxxxxxxxxx M
1N
18
#416000
b110 0
b100111 5
0>
1=
#420000
0-
08
#425000
1-
1,
b100111 J
b10010001101000101011001111000100110101011110011011110111100000001001000110100010101100111100010011010101111001101111011110000000100100011010001010110xxxxxxxxxxxxxxxxxxxxxxxxxxxxxxxxxxxxxxxxxxxxxxxxxxxxxxxxxxxxxxxxxxxxxxxxxxxxxxxxxxxxxxxxxxxxxxxxxxxx M
1N
18
#426000
b111 0
b101000 5
1>
#430000
0-
08
