Verilog repository/Design Files/Activation_Function_Block.v
`timescale 1ns / 1ps
//////////////////////////////////////////////////////////////////////////////////
// Company: University of Manchester
// Engineer: Lewis Hunton
// 
// Create Date:    16:56:39 12/14/2025 
// Design Name: 
// Module Name:    Activation_Function_Block 
// Project Name: FPGA Implementation of a MLP Artificial Neural Network Optimised for Size
// Target Devices: XC3S1500 Spartan-3
// Tool versions: Xilinx 14.2
// Description: ReLU block
//
// Dependencies: 
//
// Revision: 
// Revision 0.01 - File Created
// Additional Comments: 
//
//////////////////////////////////////////////////////////////////////////////////
module Activation_Function_Block(
    input Clk,
    input Reset,
    input wire signed [63:0] Input,
    output reg signed[63:0] Output
    );

integer i;
reg signed [7:0] Lane;
reg signed [63:0] ReLURecombined;

always @(*) begin
	for (i = 0; i < 8; i = i + 1) begin
		Lane = Input[i*8 +: 8];
		ReLURecombined[i*8 +: 8] = (Lane < 0) ? 8'sd0 : Lane;
	end
end

always @(posedge Clk) begin
	if(Reset)
		Output <= 64'd0;
	else 
		Output <= ReLURecombined;
end

endmodule

Verilog repository/Test Benches/ReLU_tb.v
`timescale 1ns / 1ps

////////////////////////////////////////////////////////////////////////////////
// Company: University of Manchester
// Engineer: Lewis Hunton
//
// Create Date:   23:20:36 04/13/2026
// Design Name:   Activation_Function_Block
// Module Name:   /home/ise/CompleteNeuralNetworkV2/ReLU_tb.v
// Project Name:  FPGA Implementation of a MLP Artificial Neural Network Optimised for Size
// Target Device:  XC3S1500 Spartan-3
// Tool versions:  Xilinx 14.2
// Description: Activation Function Test Bench
//
// Verilog Test Fixture created by ISE for module: Activation_Function_Block
//
// Dependencies:
// 
// Revision:
// Revision 0.01 - File Created
// Additional Comments:
// 
////////////////////////////////////////////////////////////////////////////////

module ReLU_tb;

	// Inputs
	reg Clk;
	reg Reset;
	reg signed [63:0] Input;

	// Outputs
	wire signed [63:0] Output;

	// Instantiate the Unit Under Test (UUT)
	Activation_Function_Block uut (
		.Clk(Clk), 
		.Reset(Reset), 
		.Input(Input), 
		.Output(Output)
	);

	//clk
	initial begin
		Clk = 0;
			forever #5 Clk = ~Clk;
	end
	
	function signed [63:0] PackLanes;
		input signed [7:0] v0, v1, v2, v3, v4, v5, v6, v7;
		begin
			PackLanes = {v7, v6, v5, v4, v3, v2, v1, v0};
		end
	endfunction
	
	function signed [63:0] ExpectedReLU;
		input signed [63:0] In;
		integer j;
		reg signed [7:0] Lane;
		begin
			for (j = 0; j <8; j = j + 1) begin
				Lane = In[j*8 +: 8];
				ExpectedReLU[j*8 +: 8] = (Lane < 0) ? 8'sd0 : Lane;
			end
		end
	endfunction
	
	task ReLUTest;
		input signed [63:0] TestInput;
		reg signed [63:0] Expected;
		begin
			Input = TestInput;
			@(posedge Clk);
			#1
			
			Expected = ExpectedReLU(TestInput);
			
			if (Output !== Expected) begin
				$display("FAIL: Input=%h Expected=%h Output=%h", TestInput, Expected, Output);
				$stop;
			end else begin
				$display("PASS: Input=%h Expected=%h Output=%h", TestInput, Expected, Output);
			end
		end
	endtask
		
	initial begin
		Reset = 1;
		Input = 64'd0;
		
		$dumpfile("ReLU_tb.vcd");
		$dumpvars(0, ReLU_tb);
		
		@(posedge Clk);
		@(posedge Clk);
		Reset = 0;
		@(posedge Clk);
		
		//Test values
		ReLUTest(PackLanes(8'sd1, 8'sd2, 8'sd3, 8'sd4, 8'sd5, 8'sd6, 8'sd7, 8'sd8));
		ReLUTest(PackLanes(-8'sd1, -8'sd2, -8'sd3, -8'sd4, -8'sd5, -8'sd6, -8'sd7, -8'sd8));
		ReLUTest(PackLanes(8'sd10, -8'sd20, 8'sd30, -8'sd40, 8'sd50, -8'sd60, 8'sd70, -8'sd80));
		ReLUTest(PackLanes(8'sd127, -8'sd128, 8'sd0, -8'sd1, 8'sd1, 8'sd127, -8'sd128, 8'sd0));
		ReLUTest(PackLanes(8'sd0, 8'sd0, 8'sd0, 8'sd0, 8'sd0, 8'sd0, 8'sd0, 8'sd0));
		ReLUTest(PackLanes(8'sd127, 8'sd127, 8'sd127, 8'sd127, 8'sd127, 8'sd127, 8'sd127, 8'sd127));
		ReLUTest(PackLanes(-8'sd128, -8'sd128, -8'sd128, -8'sd128, -8'sd128, -8'sd128, -8'sd128, -8'sd128));
		
		//random tests
		repeat (50) begin
			ReLUTest($random);
		end
		
		$display("ALL mac tests passed");
		$finish;
	end

		
endmodule

Verilog repository/Test Benches/Test Bench Results/ReLU_tb.vcd
$date
   Mon Apr 13 23:45:44 2026
$end
$version
  P.20131013
$end
$timescale
  1ps
$end
$scope module ReLU_tb $end
$var wire 1 ! Output [63] $end
$var wire 1 " Output [62] $end
$var wire 1 # Output [61] $end
$var wire 1 $ Output [60] $end
$var wire 1 % Output [59] $end
$var wire 1 & Output [58] $end
$var wire 1 ' Output [57] $end
$var wire 1 ( Output [56] $end
$var wire 1 ) Output [55] $end
$var wire 1 * Output [54] $end
$var wire 1 + Output [53] $end
$var wire 1 , Output [52] $end
$var wire 1 - Output [51] $end
$var wire 1 . Output [50] $end
$var wire 1 / Output [49] $end
$var wire 1 0 Output [48] $end
$var wire 1 1 Output [47] $end
$var wire 1 2 Output [46] $end
$var wire 1 3 Output [45] $end
$var wire 1 4 Output [44] $end
$var wire 1 5 Output [43] $end
$var wire 1 6 Output [42] $end
$var wire 1 7 Output [41] $end
$var wire 1 8 Output [40] $end
$var wire 1 9 Output [39] $end
$var wire 1 : Output [38] $end
$var wire 1 ; Output [37] $end
$var wire 1 < Output [36] $end
$var wire 1 = Output [35] $end
$var wire 1 > Output [34] $end
$var wire 1 ? Output [33] $end
$var wire 1 @ Output [32] $end
$var wire 1 A Output [31] $end
$var wire 1 B Output [30] $end
$var wire 1 C Output [29] $end
$var wire 1 D Output [28] $end
$var wire 1 E Output [27] $end
$var wire 1 F Output [26] $end
$var wire 1 G Output [25] $end
$var wire 1 H Output [24] $end
$var wire 1 I Output [23] $end
$var wire 1 J Output [22] $end
$var wire 1 K Output [21] $end
$var wire 1 L Output [20] $end
$var wire 1 M Output [19] $end
$var wire 1 N Output [18] $end
$var wire 1 O Output [17] $end
$var wire 1 P Output [16] $end
$var wire 1 Q Output [15] $end
$var wire 1 R Output [14] $end
$var wire 1 S Output [13] $end
$var wire 1 T Output [12] $end
$var wire 1 U Output [11] $end
$var wire 1 V Output [10] $end
$var wire 1 W Output [9] $end
$var wire 1 X Output [8] $end
$var wire 1 Y Output [7] $end
$var wire 1 Z Output [6] $end
$var wire 1 [ Output [5] $end
$var wire 1 \ Output [4] $end
$var wire 1 ] Output [3] $end
$var wire 1 ^ Output [2] $end
$var wire 1 _ Output [1] $end
$var wire 1 ` Output [0] $end
$var reg 1 a Clk $end
$var reg 1 b Reset $end
$var reg 64 c Input [63:0] $end
$scope function PackLanes $end
$var reg 64 d PackLanes [63:0] $end
$var reg 8 e v0 [7:0] $end
$var reg 8 f v1 [7:0] $end
$var reg 8 g v2 [7:0] $end
$var reg 8 h v3 [7:0] $end
$var reg 8 i v4 [7:0] $end
$var reg 8 j v5 [7:0] $end
$var reg 8 k v6 [7:0] $end
$var reg 8 l v7 [7:0] $end
$upscope $end
$scope function ExpectedReLU $end
$var reg 64 m ExpectedReLU [63:0] $end
$var reg 64 n In [63:0] $end
$var integer 32 o j $end
$var reg 8 p Lane [7:0] $end
$upscope $end
$scope task ReLUTest $end
$var reg 64 q TestInput [63:0] $end
$var reg 64 r Expected [63:0] $end
$upscope $end
$scope module uut $end
$var wire 1 s Clk $end
$var wire 1 t Reset $end
$var wire 1 u Input [63] $end
$var wire 1 v Input [62] $end
$var wire 1 w Input [61] $end
$var wire 1 x Input [60] $end
$var wire 1 y Input [59] $end
$var wire 1 z Input [58] $end
$var wire 1 { Input [57] $end
$var wire 1 | Input [56] $end
$var wire 1 } Input [55] $end
$var wire 1 ~ Input [54] $end
$var wire 1 !! Input [53] $end
$var wire 1 "! Input [52] $end
$var wire 1 #! Input [51] $end
$var wire 1 $! Input [50] $end
$var wire 1 %! Input [49] $end
$var wire 1 &! Input [48] $end
$var wire 1 '! Input [47] $end
$var wire 1 (! Input [46] $end
$var wire 1 )! Input [45] $end
$var wire 1 *! Input [44] $end
$var wire 1 +! Input [43] $end
$var wire 1 ,! Input [42] $end
$var wire 1 -! Input [41] $end
$var wire 1 .! Input [40] $end
$var wire 1 /! Input [39] $end
$var wire 1 0! Input [38] $end
$var wire 1 1! Input [37] $end
$var wire 1 2! Input [36] $end
$var wire 1 3! Input [35] $end
$var wire 1 4! Input [34] $end
$var wire 1 5! Input [33] $end
$var wire 1 6! Input [32] $end
$var wire 1 7! Input [31] $end
$var wire 1 8! Input [30] $end
$var wire 1 9! Input [29] $end
$var wire 1 :! Input [28] $end
$var wire 1 ;! Input [27] $end
$var wire 1 <! Input [26] $end
$var wire 1 =! Input [25] $end
$var wire 1 >! Input [24] $end
$var wire 1 ?! Input [23] $end
$var wire 1 @! Input [22] $end
$var wire 1 A! Input [21] $end
$var wire 1 B! Input [20] $end
$var wire 1 C! Input [19] $end
$var wire 1 D! Input [18] $end
$var wire 1 E! Input [17] $end
$var wire 1 F! Input [16] $end
$var wire 1 G! Input [15] $end
$var wire 1 H! Input [14] $end
$var wire 1 I! Input [13] $end
$var wire 1 J! Input [12] $end
$var wire 1 K! Input [11] $end
$var wire 1 L! Input [10] $end
$var wire 1 M! Input [9] $end
$var wire 1 N! Input [8] $end
$var wire 1 O! Input [7] $end
$var wire 1 P! Input [6] $end
$var wire 1 Q! Input [5] $end
$var wire 1 R! Input [4] $end
$var wire 1 S! Input [3] $end
$var wire 1 T! Input [2] $end
$var wire 1 U! Input [1] $end
$var wire 1 V! Input [0] $end
$var reg 64 W! Output [63:0] $end
$var integer 32 X! i $end
$var reg 8 Y! Lane [7:0] $end
$var reg 64 Z! ReLURecombined [63:0] $end
$upscope $end
$upscope $end
$enddefinitions $end
#0
$dumpvars
0a
1b
b0 c
bx d
bx e
bx f
bx g
bx h
bx i
bx j
bx k
bx l
bx m
bx n
bx o
bx p
bx q
bx r
x`
x_
x^
x]
x\
x[
xZ
xY
xX
xW
xV
xU
xT
xS
xR
xQ
xP
xO
xN
xM
xL
xK
xJ
xI
xH
xG
xF
xE
xD
xC
xB
xA
x@
x?
x>
x=
x<
x;
x:
x9
x8
x7
x6
x5
x4
x3
x2
x1
x0
x/
x.
x-
x,
x+
0s
1t
0V!
0U!
0T!
0S!
0R!
0Q!
0P!
0O!
0N!
0M!
0L!
0K!
0J!
0I!
0H!
0G!
0F!
0E!
0D!
0C!
0B!
0A!
0@!
0?!
0>!
0=!
0<!
0;!
0:!
09!
08!
x*
x)
x(
x'
x&
x%
x$
x#
x"
x!
bx W!
b1000 X!
b0 Y!
b0 Z!
07!
06!
05!
04!
03!
02!
01!
00!
0/!
0.!
0-!
0,!
0+!
0*!
0)!
0(!
0'!
0&!
0%!
0$!
0#!
0"!
0!!
0~
0}
0|
0{
0z
0y
0x
0w
0v
0u
$end
#5000
1a
0`
0_
0^
0]
0\
0[
0Z
0Y
0X
0W
0V
0U
0T
0S
0R
0Q
0P
0O
0N
0M
0L
0K
0J
0I
0H
0G
0F
0E
0D
0C
0B
0A
0@
0?
0>
0=
0<
0;
0:
09
08
07
06
05
04
03
02
01
00
0/
0.
0-
0,
0+
1s
0*
0)
0(
0'
0&
0%
0$
0#
0"
0!
b0 W!
#10000
0a
0s
#15000
1a
0b
1s
0t
#20000
0a
0s
#25000
1a
b100000000111000001100000010100000100000000110000001000000001 c
b100000000111000001100000010100000100000000110000001000000001 d
b1 e
b10 f
b11 g
b100 h
b101 i
b110 j
b111 k
b1000 l
b100000000111000001100000010100000100000000110000001000000001 q
1s
1V!
1M!
1F!
1E!
1<!
b1000 X!
b1000 Y!
b100000000111000001100000010100000100000000110000001000000001 Z!
16!
14!
1-!
1,!
1&!
1%!
1$!
1y
#30000
0a
0s
#35000
1a
1`
1W
1P
1O
1F
1@
1>
17
16
10
1/
1.
1s
1%
b100000000111000001100000010100000100000000110000001000000001 W!
#36000
b1111100011111001111110101111101111111100111111011111111011111111 c
b1111100011111001111110101111101111111100111111011111111011111111 d
b11111111 e
b11111110 f
b11111101 g
b11111100 h
b11111011 i
b11111010 j
b11111001 k
b11111000 l
b100000000111000001100000010100000100000000110000001000000001 m
b100000000111000001100000010100000100000000110000001000000001 n
b1000 o
b1000 p
b1111100011111001111110101111101111111100111111011111111011111111 q
b100000000111000001100000010100000100000000110000001000000001 r
1U!
1T!
1S!
1R!
1Q!
1P!
1O!
1L!
1K!
1J!
1I!
1H!
1G!
0E!
1D!
1C!
1B!
1A!
1@!
1?!
1;!
1:!
19!
18!
b1000 X!
b11111000 Y!
b0 Z!
17!
15!
04!
13!
12!
11!
10!
1/!
0,!
1+!
1*!
1)!
1(!
1'!
0%!
0$!
1#!
1"!
1!!
1~
1}
1x
1w
1v
1u
#40000
0a
0s
#45000
1a
0`
0W
0P
0O
0F
0@
0>
07
06
00
0/
0.
1s
0%
b0 W!
#46000
b1011000001000110110001000011001011011000000111101110110000001010 c
b1011000001000110110001000011001011011000000111101110110000001010 d
b1010 e
b11101100 f
b11110 g
b11011000 h
b110010 i
b11000100 j
b1000110 k
b10110000 l
b0 m
b1111100011111001111110101111101111111100111111011111111011111111 n
b1000 o
b11111000 p
b1011000001000110110001000011001011011000000111101110110000001010 q
b0 r
0V!
0T!
0R!
0Q!
0P!
0O!
0M!
0J!
0F!
1E!
0A!
0@!
0?!
0<!
09!
b1000 X!
b10110000 Y!
b1000110000000000011001000000000000111100000000000001010 Z!
06!
03!
00!
0/!
0-!
1,!
0+!
0*!
0)!
0&!
1%!
1$!
0#!
0"!
0!!
0}
0y
0v
#50000
0a
0s
#55000
1a
1_
1]
1O
1N
1M
1L
1?
1<
1;
1/
1.
1s
1*
b1000110000000000011001000000000000111100000000000001010 W!
#56000
b10000000011111110000000111111111000000001000000001111111 c
b10000000011111110000000111111111000000001000000001111111 d
b1111111 e
b10000000 f
b0 g
b11111111 h
b1 i
b1111111 j
b10000000 k
b0 l
b1000110000000000011001000000000000111100000000000001010 m
b1011000001000110110001000011001011011000000111101110110000001010 n
b1000 o
b10110000 p
b10000000011111110000000111111111000000001000000001111111 q
b1000110000000000011001000000000000111100000000000001010 r
1V!
1T!
1R!
1Q!
1P!
0L!
0K!
0I!
0H!
0E!
0D!
0C!
0B!
1>!
1=!
1<!
19!
b1000 X!
b0 Y!
b11111110000000100000000000000000000000001111111 Z!
16!
05!
02!
01!
1.!
1-!
1+!
1*!
1)!
0'!
0%!
0$!
0~
1}
0x
0w
0u
#60000
0a
0s
#65000
1a
1`
1^
1\
1[
1Z
0O
0N
0M
0L
1@
0?
0<
0;
18
17
16
15
14
13
12
0/
0.
1s
0*
b11111110000000100000000000000000000000001111111 W!
#66000
b0 c
b0 d
b0 e
b0 f
b0 h
b0 i
b0 j
b0 k
b11111110000000100000000000000000000000001111111 m
b10000000011111110000000111111111000000001000000001111111 n
b1000 o
b0 p
b0 q
b11111110000000100000000000000000000000001111111 r
0V!
0U!
0T!
0S!
0R!
0Q!
0P!
0G!
0>!
0=!
0<!
0;!
0:!
09!
08!
b1000 X!
b0 Z!
07!
06!
0.!
0-!
0,!
0+!
0*!
0)!
0(!
0}
#70000
0a
0s
#75000
1a
0`
0_
0^
0]
0\
0[
0Z
0@
08
07
06
05
04
03
02
1s
b0 W!
#76000
b111111101111111011111110111111101111111011111110111111101111111 c
b111111101111111011111110111111101111111011111110111111101111111 d
b1111111 e
b1111111 f
b1111111 g
b1111111 h
b1111111 i
b1111111 j
b1111111 k
b1111111 l
b0 m
b0 n
b1000 o
b111111101111111011111110111111101111111011111110111111101111111 q
b0 r
1V!
1U!
1T!
1S!
1R!
1Q!
1P!
1N!
1M!
1L!
1K!
1J!
1I!
1H!
1F!
1E!
1D!
1C!
1B!
1A!
1@!
1>!
1=!
1<!
1;!
1:!
19!
18!
b1000 X!
b1111111 Y!
b111111101111111011111110111111101111111011111110111111101111111 Z!
16!
15!
14!
13!
12!
11!
10!
1.!
1-!
1,!
1+!
1*!
1)!
1(!
1&!
1%!
1$!
1#!
1"!
1!!
1~
1|
1{
1z
1y
1x
1w
1v
#80000
0a
0s
#85000
1a
1`
1_
1^
1]
1\
1[
1Z
1X
1W
1V
1U
1T
1S
1R
1P
1O
1N
1M
1L
1K
1J
1H
1G
1F
1E
1D
1C
1B
1@
1?
1>
1=
1<
1;
1:
18
17
16
15
14
13
12
10
1/
1.
1-
1,
1+
1s
1*
1(
1'
1&
1%
1$
1#
1"
b111111101111111011111110111111101111111011111110111111101111111 W!
#86000
b1000000010000000100000001000000010000000100000001000000010000000 c
b1000000010000000100000001000000010000000100000001000000010000000 d
b10000000 e
b10000000 f
b10000000 g
b10000000 h
b10000000 i
b10000000 j
b10000000 k
b10000000 l
b111111101111111011111110111111101111111011111110111111101111111 m
b111111101111111011111110111111101111111011111110111111101111111 n
b1000 o
b1111111 p
b1000000010000000100000001000000010000000100000001000000010000000 q
b111111101111111011111110111111101111111011111110111111101111111 r
0V!
0U!
0T!
0S!
0R!
0Q!
0P!
1O!
0N!
0M!
0L!
0K!
0J!
0I!
0H!
1G!
0F!
0E!
0D!
0C!
0B!
0A!
0@!
1?!
0>!
0=!
0<!
0;!
0:!
09!
08!
b1000 X!
b10000000 Y!
b0 Z!
17!
06!
05!
04!
03!
02!
01!
00!
1/!
0.!
0-!
0,!
0+!
0*!
0)!
0(!
1'!
0&!
0%!
0$!
0#!
0"!
0!!
0~
1}
0|
0{
0z
0y
0x
0w
0v
1u
#90000
0a
0s
#95000
1a
0`
0_
0^
0]
0\
0[
0Z
0X
0W
0V
0U
0T
0S
0R
0P
0O
0N
0M
0L
0K
0J
0H
0G
0F
0E
0D
0C
0B
0@
0?
0>
0=
0<
0;
0:
08
07
06
05
04
03
02
00
0/
0.
0-
0,
0+
1s
0*
0(
0'
0&
0%
0$
0#
0"
b0 W!
#96000
b10010000101010011010100100100 c
b0 m
b1000000010000000100000001000000010000000100000001000000010000000 n
b1000 o
b10000000 p
b10010000101010011010100100100 q
b0 r
1T!
1Q!
0O!
1N!
1L!
1J!
1I!
0G!
1F!
1D!
1B!
0?!
1=!
1:!
b1000 X!
b0 Y!
b10010000101010011010100100100 Z!
07!
0/!
0'!
0}
0u
#100000
0a
0s
#105000
1a
1^
1[
1X
1V
1T
1S
1P
1N
1L
1G
1D
1s
b10010000101010011010100100100 W!
#106000
b1111111111111111111111111111111111000000100010010101111010000001 c
b10010000101010011010100100100 m
b10010000101010011010100100100 n
b1000 o
b0 p
b1111111111111111111111111111111111000000100010010101111010000001 q
b10010000101010011010100100100 r
1V!
0T!
0Q!
1O!
0N!
1M!
1K!
0I!
1H!
0D!
1C!
0B!
1?!
0=!
0:!
18!
b1000 X!
b11111111 Y!
b101111000000000 Z!
17!
16!
15!
14!
13!
12!
11!
10!
1/!
1.!
1-!
1,!
1+!
1*!
1)!
1(!
1'!
1&!
1%!
1$!
1#!
1"!
1!!
1~
1}
1|
1{
1z
1y
1x
1w
1v
1u
#110000
0a
0s
#115000
1a
0^
0[
0X
1W
1U
0S
1R
0P
0N
0L
0G
0D
1s
b101111000000000 W!
#116000
b1111111111111111111111111111111110000100100001001101011000001001 c
b101111000000000 m
b1111111111111111111111111111111111000000100010010101111010000001 n
b1000 o
b11111111 p
b1111111111111111111111111111111110000100100001001101011000001001 q
b101111000000000 r
1S!
0O!
0K!
1G!
0F!
1D!
0C!
1<!
08!
b1000 X!
b11111111 Y!
b1001 Z!
#120000
0a
0s
#125000
1a
1`
1]
0W
0V
0U
0T
0R
1s
b1001 W!
#126000
b1111111111111111111111111111111110110001111100000101011001100011 c
b1001 m
b1111111111111111111111111111111110000100100001001101011000001001 n
b1000 o
b11111111 p
b1111111111111111111111111111111110110001111100000101011001100011 q
b1001 r
1U!
0S!
1Q!
1P!
0G!
0D!
1B!
1A!
1@!
1>!
0<!
1:!
19!
b1000 X!
b11111111 Y!
b101011001100011 Z!
#130000
0a
0s
#135000
1a
1_
0]
1[
1Z
1W
1V
1T
1R
1s
b101011001100011 W!
#136000
b110101110010111101100001101 c
b101011001100011 m
b1111111111111111111111111111111110110001111100000101011001100011 n
b1000 o
b11111111 p
b110101110010111101100001101 q
b101011001100011 r
0U!
1T!
1S!
0Q!
0P!
1N!
0L!
1K!
1I!
1F!
1C!
0@!
0>!
1=!
1<!
0:!
09!
b1000 X!
b0 Y!
b110000000000111101100001101 Z!
07!
06!
05!
04!
03!
02!
01!
00!
0/!
0.!
0-!
0,!
0+!
0*!
0)!
0(!
0'!
0&!
0%!
0$!
0#!
0"!
0!!
0~
0}
0|
0{
0z
0y
0x
0w
0v
0u
#140000
0a
0s
#145000
1a
0_
1^
1]
0[
0Z
1X
0V
1U
1S
1G
1F
1s
b110000000000111101100001101 W!
#146000
b1000110110111111001100110001101 c
b110000000000111101100001101 m
b110101110010111101100001101 n
b1000 o
b0 p
b1000110110111111001100110001101 q
b110000000000111101100001101 r
1O!
0M!
0I!
0H!
1G!
1E!
1D!
0A!
1@!
18!
b1000 X!
b0 Y!
b1000110000000000000000000000000 Z!
#150000
0a
0s
#155000
1a
0`
0^
0]
0X
0W
0U
0T
0S
0R
1B
1s
b1000110000000000000000000000000 W!
#156000
b1111111111111111111111111111111110110010110000101000010001100101 c
b1000110000000000000000000000000 m
b1000110110111111001100110001101 n
b1000 o
b0 p
b1111111111111111111111111111111110110010110000101000010001100101 q
b1000110000000000000000000000000 r
0S!
1Q!
1P!
0O!
0N!
1L!
0K!
0J!
0F!
0D!
0C!
0B!
0<!
1:!
19!
08!
b1000 X!
b11111111 Y!
b1100101 Z!
17!
16!
15!
14!
13!
12!
11!
10!
1/!
1.!
1-!
1,!
1+!
1*!
1)!
1(!
1'!
1&!
1%!
1$!
1#!
1"!
1!!
1~
1}
1|
1{
1z
1y
1x
1w
1v
1u
#160000
0a
0s
#165000
1a
1`
1^
1[
1Z
0G
0F
0B
1s
b1100101 W!
#166000
b1111111111111111111111111111111110001001001101110101001000010010 c
b1100101 m
b1111111111111111111111111111111110110010110000101000010001100101 n
b1000 o
b11111111 p
b1111111111111111111111111111111110001001001101110101001000010010 q
b1100101 r
0V!
1U!
0T!
1R!
0Q!
0P!
1M!
0L!
1J!
1H!
0G!
1F!
1D!
1B!
1A!
0@!
0?!
1>!
0=!
1;!
0:!
09!
b1000 X!
b11111111 Y!
b1101110101001000010010 Z!
#170000
0a
0s
#175000
1a
0`
1_
0^
1\
0[
0Z
1W
1T
1R
1P
1O
1N
1L
1K
1s
b1101110101001000010010 W!
#176000
b111100111110001100000001 c
b1101110101001000010010 m
b1111111111111111111111111111111110001001001101110101001000010010 n
b1000 o
b11111111 p
b111100111110001100000001 q
b1101110101001000010010 r
1V!
0U!
0R!
1N!
0J!
1I!
1G!
0D!
1@!
1?!
0>!
0;!
b1000 X!
b0 Y!
b1 Z!
07!
06!
05!
04!
03!
02!
01!
00!
0/!
0.!
0-!
0,!
0+!
0*!
0)!
0(!
0'!
0&!
0%!
0$!
0#!
0"!
0!!
0~
0}
0|
0{
0z
0y
0x
0w
0v
0u
#180000
0a
0s
#185000
1a
1`
0_
0\
0W
0T
0R
0P
0O
0N
0L
0K
1s
b1 W!
#186000
b110110101111100110100001101 c
b1 m
b111100111110001100000001 n
b1000 o
b0 p
b110110101111100110100001101 q
b1 r
1T!
1S!
0M!
1L!
1K!
0I!
1D!
0A!
1=!
1<!
b1000 X!
b0 Y!
b110000000000000000000001101 Z!
#190000
0a
0s
#195000
1a
1^
1]
1G
1F
1s
b110000000000000000000001101 W!
#196000
b111011001000111111000101110110 c
b110000000000000000000001101 m
b110110101111100110100001101 n
b1000 o
b0 p
b111011001000111111000101110110 q
b110000000000000000000001101 r
0V!
1U!
0S!
1R!
1Q!
1P!
0L!
0K!
1J!
1I!
0D!
0B!
1A!
0@!
0?!
1>!
0<!
1;!
1:!
19!
b1000 X!
b0 Y!
b111011001000110000000001110110 Z!
#200000
0a
0s
#205000
1a
0`
1_
0]
1\
1[
1Z
1P
1O
1K
1H
0F
1E
1D
1C
1s
b111011001000110000000001110110 W!
#206000
b11110100011011100110100111101 c
b111011001000110000000001110110 m
b111011001000111111000101110110 n
b1000 o
b0 p
b11110100011011100110100111101 q
b111011001000110000000001110110 r
1V!
0U!
1S!
0P!
1L!
1K!
0J!
0I!
0E!
1D!
1C!
0A!
1?!
0>!
1<!
09!
b1000 X!
b0 Y!
b11110000000000000000000111101 Z!
#210000
0a
0s
#215000
1a
1`
0_
1]
0Z
0P
0O
0K
0H
1F
0C
1s
b11110000000000000000000111101 W!
#216000
b1110110110101000101011111101101 c
b11110000000000000000000111101 m
b11110100011011100110100111101 n
b1000 o
b0 p
b1110110110101000101011111101101 q
b11110000000000000000000111101 r
0R!
1P!
1O!
1M!
0K!
1J!
0G!
0F!
0C!
1B!
1@!
0;!
19!
18!
b1000 X!
b0 Y!
b1110110000000000101011100000000 Z!
#220000
0a
0s
#225000
1a
0`
0^
0]
0\
0[
1X
1W
1V
1T
1R
0E
1C
1B
1s
b1110110000000000101011100000000 W!
#226000
b1000110001011011111011110001100 c
b1110110000000000101011100000000 m
b1110110110101000101011111101101 n
b1000 o
b0 p
b1000110001011011111011110001100 q
b1110110000000000101011100000000 r
0V!
0Q!
0P!
1I!
1G!
1F!
1C!
0B!
1A!
0@!
0?!
0:!
09!
b1000 X!
b0 Y!
b1000110001011010000000000000000 Z!
#230000
0a
0s
#235000
1a
0X
0W
0V
0T
0R
1P
1N
1M
1K
0D
0C
1s
b1000110001011010000000000000000 W!
#236000
b1111100111111011110100111111001 c
b1000110001011010000000000000000 m
b1000110001011011111011110001100 n
b1000 o
b0 p
b1111100111111011110100111111001 q
b1000110001011010000000000000000 r
1V!
0T!
1R!
1Q!
1P!
0M!
0L!
1K!
0J!
1B!
1@!
1?!
0=!
1;!
1:!
19!
b1000 X!
b0 Y!
b1111100000000000000000000000000 Z!
#240000
0a
0s
#245000
1a
0P
0N
0M
0K
0G
1E
1D
1C
1s
b1111100000000000000000000000000 W!
#246000
b1111111111111111111111111111111111100011001101110010010011000110 c
b1111100000000000000000000000000 m
b1111100111111011110100111111001 n
b1000 o
b0 p
b1111111111111111111111111111111111100011001101110010010011000110 q
b1111100000000000000000000000000 r
0V!
1U!
1T!
0S!
0R!
0Q!
0N!
1L!
0K!
0H!
0G!
1E!
0C!
0@!
0?!
1>!
1=!
0<!
0;!
0:!
b1000 X!
b11111111 Y!
b1101110010010000000000 Z!
17!
16!
15!
14!
13!
12!
11!
10!
1/!
1.!
1-!
1,!
1+!
1*!
1)!
1(!
1'!
1&!
1%!
1$!
1#!
1"!
1!!
1~
1}
1|
1{
1z
1y
1x
1w
1v
1u
#250000
0a
0s
#255000
1a
1V
1S
1P
1O
1N
1L
1K
0F
0E
0D
0C
0B
1s
b1101110010010000000000 W!
#256000
b1111111111111111111111111111111111100010111101111000010011000101 c
b1101110010010000000000 m
b1111111111111111111111111111111111100011001101110010010011000110 n
b1000 o
b11111111 p
b1111111111111111111111111111111111100010111101111000010011000101 q
b1101110010010000000000 r
1V!
0U!
0I!
1G!
1@!
1?!
0>!
b1000 X!
b11111111 Y!
b0 Z!
#260000
0a
0s
#265000
1a
0V
0S
0P
0O
0N
0L
0K
1s
b0 W!
#266000
b1111111111111111111111111111111111010101000100111101001010101010 c
b0 m
b1111111111111111111111111111111111100010111101111000010011000101 n
b1000 o
b11111111 p
b1111111111111111111111111111111111010101000100111101001010101010 q
b0 r
0V!
1U!
0T!
1S!
1Q!
0P!
1M!
0L!
1J!
1H!
0D!
0A!
0@!
0?!
1>!
0=!
1<!
1:!
09!
b1000 X!
b11111111 Y!
b100110000000000000000 Z!
#270000
0a
0s
#275000
1a
1P
1O
1L
1s
b100110000000000000000 W!
#276000
b1110010101011111111011111100101 c
b100110000000000000000 m
b1111111111111111111111111111111111010101000100111101001010101010 n
b1000 o
b11111111 p
b1110010101011111111011111100101 q
b100110000000000000000 r
1V!
0U!
1T!
0S!
1P!
1N!
1L!
1I!
1D!
1C!
0B!
1A!
1?!
0>!
1=!
0<!
19!
b1000 X!
b0 Y!
b1110010000000000000000000000000 Z!
07!
06!
05!
04!
03!
02!
01!
00!
0/!
0.!
0-!
0,!
0+!
0*!
0)!
0(!
0'!
0&!
0%!
0$!
0#!
0"!
0!!
0~
0}
0|
0{
0z
0y
0x
0w
0v
0u
#280000
0a
0s
#285000
1a
0P
0O
0L
1G
1D
1C
1B
1s
b1110010000000000000000000000000 W!
#286000
b1111111111111111111111111111111110111011110100100111001001110111 c
b1110010000000000000000000000000 m
b1110010101011111111011111100101 n
b1000 o
b0 p
b1111111111111111111111111111111110111011110100100111001001110111 q
b1110010000000000000000000000000 r
1U!
1R!
0O!
0N!
0L!
0G!
0F!
0D!
0C!
1B!
0A!
1@!
1>!
1;!
08!
b1000 X!
b11111111 Y!
b111001001110111 Z!
17!
16!
15!
14!
13!
12!
11!
10!
1/!
1.!
1-!
1,!
1+!
1*!
1)!
1(!
1'!
1&!
1%!
1$!
1#!
1"!
1!!
1~
1}
1|
1{
1z
1y
1x
1w
1v
1u
#290000
0a
0s
#295000
1a
1`
1_
1^
1\
1[
1Z
1W
1T
1S
1R
0G
0D
0C
0B
1s
b111001001110111 W!
#296000
b1111111111111111111111111111111110001001001100101101011000010010 c
b111001001110111 m
b1111111111111111111111111111111110111011110100100111001001110111 n
b1000 o
b11111111 p
b1111111111111111111111111111111110001001001100101101011000010010 q
b111001001110111 r
0V!
0T!
0Q!
0P!
1L!
0I!
1G!
1A!
0@!
0?!
0=!
0:!
09!
b1000 X!
b11111111 Y!
b1100100000000000010010 Z!
#300000
0a
0s
