Verilog repository/Design Files/Scratchpad.v
`timescale 1ns / 1ps
//////////////////////////////////////////////////////////////////////////////////
// Company: University of Manchester
// Engineer: Lewis Hunton
// 
// Create Date:    00:50:48 02/27/2026 
// Design Name: 
// Module Name:    Scratchpad 
// Project Name: FPGA Implementation of a MLP Artificial Neural Network Optimised for Size
// Target Devices: XC3S1500 Spartan-3
// Tool versions: Xilinx 14.2
// Description: Scratchpad
//
// Dependencies: 
//
// Revision: 
// Revision 0.01 - File Created
// Additional Comments: 
//
//////////////////////////////////////////////////////////////////////////////////
module Scratchpad(
	input wire Clk,
	input wire Reset,
	
	input wire WriteEnable, 
	input wire [4:0] WriteAddress,
	input wire [63:0] WriteData,
	
	input wire [4:0] ReadAddress,
	output wire [63:0] ReadData
    );

	reg [63:0] ScratchPadMemory [0:31];
	reg toggle; 
	
	integer i;
	
	always @ (posedge Clk) begin
		if (Reset) begin
			for (i=0 ; i<32; i = i + 1)
				ScratchPadMemory[i] <= 64'd0;
				
		end else if (WriteEnable) begin
			ScratchPadMemory[WriteAddress] <= WriteData;
		end
	end
			
	assign ReadData = ScratchPadMemory[ReadAddress];
		
endmodule

Verilog repository/Test Benches/Scratchpad_tb.v
`timescale 1ns / 1ps

////////////////////////////////////////////////////////////////////////////////
// Company: University of Manchester
// Engineer: Lewis Hunton
//
// Create Date:   03:01:14 04/14/2026
// Design Name:   Scratchpad
// Module Name:   /home/ise/CompleteNeuralNetworkV2/Scratchpad_tb.v
// Project Name:  FPGA Implementation of a MLP Artificial Neural Network Optimised for Size
// Target Device:  XC3S1500 Spartan-3
// Tool versions:  Xilinx 14.2
// Description: Scratchpad Test Bench
//
// Verilog Test Fixture created by ISE for module: Scratchpad
//
// Dependencies:
// 
// Revision:
// Revision 0.01 - File Created
// Additional Comments:
// 
////////////////////////////////////////////////////////////////////////////////

module Scratchpad_tb;

	// Inputs
	reg Clk;
	reg Reset;
	reg WriteEnable;
	reg [4:0] WriteAddress;
	reg [63:0] WriteData;
	reg [4:0] ReadAddress;

	// Outputs
	wire [63:0] ReadData;

	// Instantiate the Unit Under Test (UUT)
	Scratchpad uut (
		.Clk(Clk), 
		.Reset(Reset), 
		.WriteEnable(WriteEnable), 
		.WriteAddress(WriteAddress), 
		.WriteData(WriteData), 
		.ReadAddress(ReadAddress), 
		.ReadData(ReadData)
	);
	
initial begin
	Clk = 0;
	forever #5 Clk = ~Clk;
end

integer Failed;
integer i;

task Write;
	input [4:0] Addr;
	input [63:0] Data;
	begin
		@(posedge Clk);
		#1;
		WriteEnable = 1;
		WriteAddress = Addr;
		WriteData = Data;
		@(posedge Clk);
		#1;
		WriteEnable = 0;
	end
endtask

task CheckRead;
	input [4:0] Addr;
	input [63:0] Expected;
	begin
		ReadAddress = Addr;
		#1;
		if(ReadData !== Expected) begin
			$display("FAIL (read): ADDR=%0d Expected=%h Output=%h", Addr, Expected, ReadData);
			Failed = Failed + 1;
		end else begin
			$display("PASS (read): Addr=%0d Data=%h", Addr, ReadData);
		end
	end
endtask

initial  begin
	Failed = 0;
	Reset = 1;
	WriteEnable = 0;
	WriteAddress = 0;
	WriteData = 0;
	ReadAddress = 0;
	
	$dumpfile("Scratchpad_tb.vcd");
	$dumpvars(0, Scratchpad_tb);
	
	@(posedge Clk)
	#1;
	@(posedge Clk)
	#1;
	Reset = 0;
	@(posedge Clk)
	#1;
	
	$display("Test 1: Reset Clears all locations");
	for (i = 0; i < 32; i = i + 1)
		CheckRead(i[4:0], 64'd0);
	
	$display("Test 2: Write and Readback all locations");
	for(i = 0; i < 32; i = i + 1)
		Write(i[4:0], 64'hDEADBEEFCAFE0000 | i);
		
	for (i = 0; i < 32; i = i + 1)
		CheckRead(i[4:0], 64'hDEADBEEFCAFE0000 | i);
	
	$display("Test 3: Asynch read updates immediatly on address cahnge");
	Write(5'd5, 64'hAAAAAAAAAAAAAAAA);
	Write (5'd6, 64'hBBBBBBBBBBBBBBBB);
	
	ReadAddress = 5'd5;
	#1;
	
	if(ReadData !== 64'hAAAAAAAAAAAAAAAA) begin
		$display("FAIL (asynch): Addr=5 expected 16*A Output=%h", ReadData);
		Failed = Failed + 1;
	end else 
		$display("PASS (asynch): Addr=5 immediate read correct");
		
	ReadAddress = 5'd6;
	#1;
	
	if(ReadData !== 64'hBBBBBBBBBBBBBBBB) begin
		$display("FAIL (asynch): Addr=6 expected 16*B Output=%h", ReadData);
		Failed = Failed + 1;
	end else 
		$display("PASS (asynch): Addr=6 immediate read correct");	
		
	$display("Test 4: WriteEnable gate");
	Write(5'd10, 64'hCAFECAFECAFECAFE);
	
	@(posedge Clk);
	#1;
	WriteEnable = 0;
	WriteAddress = 5'd10;
	WriteData = 64'hDEADDEADDEADDEAD;
	@(posedge Clk);
	#1;
	
	CheckRead(5'd10, 64'hCAFECAFECAFECAFE);
	
	$display("Test 5: Overwrite");
	Write(5'd15, 64'h1111111111111111);
	CheckRead(5'd15, 64'h1111111111111111);
	Write(5'd15, 64'h2222222222222222);
	CheckRead(5'd15, 64'h2222222222222222);

	$display("Test 6: Boundary addresses");
	Write(5'd0, 64'hFFFFFFFFFFFFFFFF);
	Write(5'd31, 64'h0000000000000001);
	CheckRead(5'd0, 64'hFFFFFFFFFFFFFFFF);
	CheckRead(5'd31, 64'h0000000000000001);
	
	$display("Test 7: Reset after writes");
	Reset = 1;
	@(posedge Clk);
	#1;
	@(posedge Clk);
	#1;
	Reset = 0;
	@(posedge Clk);
	#1;
	for(i = 0; i < 32; i = i + 1)
		CheckRead(i[4:0], 64'd0);
	
	$display("Test 8: Read whioe writing different address");
	Write(5'd20, 64'hFACEFACEFACEFACE);
	ReadAddress = 5'd20;
	
	@(posedge Clk);
	#1;
	WriteEnable = 1;
	WriteAddress = 5'd21;
	WriteData = 64'h9999999999999999;
	#1;
	if(ReadData !== 64'hFACEFACEFACEFACE) begin
		$display("FAIL (concurrent): Read distributed by write to a different address, Output=%h", ReadData);
		Failed = Failed + 1;
	end else
		$display("PASS (concurrent): Read unaffected by write to different address");
	@(posedge Clk);
	#1;
	WriteEnable = 0;
	
	if (Failed == 0)
		$display ("ALL scratchpad tests passed");
	else
		$display ("FAILED: 0%d tests failed", Failed);
		
	$finish;
end
      
endmodule

Verilog repository/Test Benches/Test Bench Results/Scratchpad_tb.vcd
$date
   Tue Apr 14 03:37:01 2026
$end
$version
  P.20131013
$end
$timescale
  1ps
$end
$scope module Scratchpad_tb $end
$var wire 1 \! ReadData [63] $end
$var wire 1 ]! ReadData [62] $end
$var wire 1 ^! ReadData [61] $end
$var wire 1 _! ReadData [60] $end
$var wire 1 `! ReadData [59] $end
$var wire 1 a! ReadData [58] $end
$var wire 1 b! ReadData [57] $end
$var wire 1 c! ReadData [56] $end
$var wire 1 d! ReadData [55] $end
$var wire 1 e! ReadData [54] $end
$var wire 1 f! ReadData [53] $end
$var wire 1 g! ReadData [52] $end
$var wire 1 h! ReadData [51] $end
$var wire 1 i! ReadData [50] $end
$var wire 1 j! ReadData [49] $end
$var wire 1 k! ReadData [48] $end
$var wire 1 l! ReadData [47] $end
$var wire 1 m! ReadData [46] $end
$var wire 1 n! ReadData [45] $end
$var wire 1 o! ReadData [44] $end
$var wire 1 p! ReadData [43] $end
$var wire 1 q! ReadData [42] $end
$var wire 1 r! ReadData [41] $end
$var wire 1 s! ReadData [40] $end
$var wire 1 t! ReadData [39] $end
$var wire 1 u! ReadData [38] $end
$var wire 1 v! ReadData [37] $end
$var wire 1 w! ReadData [36] $end
$var wire 1 x! ReadData [35] $end
$var wire 1 y! ReadData [34] $end
$var wire 1 z! ReadData [33] $end
$var wire 1 {! ReadData [32] $end
$var wire 1 |! ReadData [31] $end
$var wire 1 }! ReadData [30] $end
$var wire 1 ~! ReadData [29] $end
$var wire 1 !" ReadData [28] $end
$var wire 1 "" ReadData [27] $end
$var wire 1 #" ReadData [26] $end
$var wire 1 $" ReadData [25] $end
$var wire 1 %" ReadData [24] $end
$var wire 1 &" ReadData [23] $end
$var wire 1 '" ReadData [22] $end
$var wire 1 (" ReadData [21] $end
$var wire 1 )" ReadData [20] $end
$var wire 1 *" ReadData [19] $end
$var wire 1 +" ReadData [18] $end
$var wire 1 ," ReadData [17] $end
$var wire 1 -" ReadData [16] $end
$var wire 1 ." ReadData [15] $end
$var wire 1 /" ReadData [14] $end
$var wire 1 0" ReadData [13] $end
$var wire 1 1" ReadData [12] $end
$var wire 1 2" ReadData [11] $end
$var wire 1 3" ReadData [10] $end
$var wire 1 4" ReadData [9] $end
$var wire 1 5" ReadData [8] $end
$var wire 1 6" ReadData [7] $end
$var wire 1 7" ReadData [6] $end
$var wire 1 8" ReadData [5] $end
$var wire 1 9" ReadData [4] $end
$var wire 1 :" ReadData [3] $end
$var wire 1 ;" ReadData [2] $end
$var wire 1 <" ReadData [1] $end
$var wire 1 =" ReadData [0] $end
$var reg 1 a Clk $end
$var reg 1 b Reset $end
$var reg 1 c WriteEnable $end
$var reg 5 d WriteAddress [4:0] $end
$var reg 64 e WriteData [63:0] $end
$var reg 5 f ReadAddress [4:0] $end
$var integer 32 g Failed $end
$var integer 32 h i $end
$scope task Write $end
$var reg 5 i Addr [4:0] $end
$var reg 64 j Data [63:0] $end
$upscope $end
$scope task CheckRead $end
$var reg 5 k Addr [4:0] $end
$var reg 64 l Expected [63:0] $end
$upscope $end
$scope module uut $end
$var wire 1 m Clk $end
$var wire 1 n Reset $end
$var wire 1 o WriteEnable $end
$var wire 1 p WriteAddress [4] $end
$var wire 1 q WriteAddress [3] $end
$var wire 1 r WriteAddress [2] $end
$var wire 1 s WriteAddress [1] $end
$var wire 1 t WriteAddress [0] $end
$var wire 1 u WriteData [63] $end
$var wire 1 v WriteData [62] $end
$var wire 1 w WriteData [61] $end
$var wire 1 x WriteData [60] $end
$var wire 1 y WriteData [59] $end
$var wire 1 z WriteData [58] $end
$var wire 1 { WriteData [57] $end
$var wire 1 | WriteData [56] $end
$var wire 1 } WriteData [55] $end
$var wire 1 ~ WriteData [54] $end
$var wire 1 !! WriteData [53] $end
$var wire 1 "! WriteData [52] $end
$var wire 1 #! WriteData [51] $end
$var wire 1 $! WriteData [50] $end
$var wire 1 %! WriteData [49] $end
$var wire 1 &! WriteData [48] $end
$var wire 1 '! WriteData [47] $end
$var wire 1 (! WriteData [46] $end
$var wire 1 )! WriteData [45] $end
$var wire 1 *! WriteData [44] $end
$var wire 1 +! WriteData [43] $end
$var wire 1 ,! WriteData [42] $end
$var wire 1 -! WriteData [41] $end
$var wire 1 .! WriteData [40] $end
$var wire 1 /! WriteData [39] $end
$var wire 1 0! WriteData [38] $end
$var wire 1 1! WriteData [37] $end
$var wire 1 2! WriteData [36] $end
$var wire 1 3! WriteData [35] $end
$var wire 1 4! WriteData [34] $end
$var wire 1 5! WriteData [33] $end
$var wire 1 6! WriteData [32] $end
$var wire 1 7! WriteData [31] $end
$var wire 1 8! WriteData [30] $end
$var wire 1 9! WriteData [29] $end
$var wire 1 :! WriteData [28] $end
$var wire 1 ;! WriteData [27] $end
$var wire 1 <! WriteData [26] $end
$var wire 1 =! WriteData [25] $end
$var wire 1 >! WriteData [24] $end
$var wire 1 ?! WriteData [23] $end
$var wire 1 @! WriteData [22] $end
$var wire 1 A! WriteData [21] $end
$var wire 1 B! WriteData [20] $end
$var wire 1 C! WriteData [19] $end
$var wire 1 D! WriteData [18] $end
$var wire 1 E! WriteData [17] $end
$var wire 1 F! WriteData [16] $end
$var wire 1 G! WriteData [15] $end
$var wire 1 H! WriteData [14] $end
$var wire 1 I! WriteData [13] $end
$var wire 1 J! WriteData [12] $end
$var wire 1 K! WriteData [11] $end
$var wire 1 L! WriteData [10] $end
$var wire 1 M! WriteData [9] $end
$var wire 1 N! WriteData [8] $end
$var wire 1 O! WriteData [7] $end
$var wire 1 P! WriteData [6] $end
$var wire 1 Q! WriteData [5] $end
$var wire 1 R! WriteData [4] $end
$var wire 1 S! WriteData [3] $end
$var wire 1 T! WriteData [2] $end
$var wire 1 U! WriteData [1] $end
$var wire 1 V! WriteData [0] $end
$var wire 1 W! ReadAddress [4] $end
$var wire 1 X! ReadAddress [3] $end
$var wire 1 Y! ReadAddress [2] $end
$var wire 1 Z! ReadAddress [1] $end
$var wire 1 [! ReadAddress [0] $end
$var wire 1 \! ReadData [63] $end
$var wire 1 ]! ReadData [62] $end
$var wire 1 ^! ReadData [61] $end
$var wire 1 _! ReadData [60] $end
$var wire 1 `! ReadData [59] $end
$var wire 1 a! ReadData [58] $end
$var wire 1 b! ReadData [57] $end
$var wire 1 c! ReadData [56] $end
$var wire 1 d! ReadData [55] $end
$var wire 1 e! ReadData [54] $end
$var wire 1 f! ReadData [53] $end
$var wire 1 g! ReadData [52] $end
$var wire 1 h! ReadData [51] $end
$var wire 1 i! ReadData [50] $end
$var wire 1 j! ReadData [49] $end
$var wire 1 k! ReadData [48] $end
$var wire 1 l! ReadData [47] $end
$var wire 1 m! ReadData [46] $end
$var wire 1 n! ReadData [45] $end
$var wire 1 o! ReadData [44] $end
$var wire 1 p! ReadData [43] $end
$var wire 1 q! ReadData [42] $end
$var wire 1 r! ReadData [41] $end
$var wire 1 s! ReadData [40] $end
$var wire 1 t! ReadData [39] $end
$var wire 1 u! ReadData [38] $end
$var wire 1 v! ReadData [37] $end
$var wire 1 w! ReadData [36] $end
$var wire 1 x! ReadData [35] $end
$var wire 1 y! ReadData [34] $end
$var wire 1 z! ReadData [33] $end
$var wire 1 {! ReadData [32] $end
$var wire 1 |! ReadData [31] $end
$var wire 1 }! ReadData [30] $end
$var wire 1 ~! ReadData [29] $end
$var wire 1 !" ReadData [28] $end
$var wire 1 "" ReadData [27] $end
$var wire 1 #" ReadData [26] $end
$var wire 1 $" ReadData [25] $end
$var wire 1 %" ReadData [24] $end
$var wire 1 &" ReadData [23] $end
$var wire 1 '" ReadData [22] $end
$var wire 1 (" ReadData [21] $end
$var wire 1 )" ReadData [20] $end
$var wire 1 *" ReadData [19] $end
$var wire 1 +" ReadData [18] $end
$var wire 1 ," ReadData [17] $end
$var wire 1 -" ReadData [16] $end
$var wire 1 ." ReadData [15] $end
$var wire 1 /" ReadData [14] $end
$var wire 1 0" ReadData [13] $end
$var wire 1 1" ReadData [12] $end
$var wire 1 2" ReadData [11] $end
$var wire 1 3" ReadData [10] $end
$var wire 1 4" ReadData [9] $end
$var wire 1 5" ReadData [8] $end
$var wire 1 6" ReadData [7] $end
$var wire 1 7" ReadData [6] $end
$var wire 1 8" ReadData [5] $end
$var wire 1 9" ReadData [4] $end
$var wire 1 :" ReadData [3] $end
$var wire 1 ;" ReadData [2] $end
$var wire 1 <" ReadData [1] $end
$var wire 1 =" ReadData [0] $end
$var reg 2048 >" ScratchPadMemory [63:0] $end
$var reg 1 ?" toggle $end
$var integer 32 @" i $end
$upscope $end
$upscope $end
$enddefinitions $end
#0
$dumpvars
0a
1b
0c
b0 d
b0 e
b0 f
b0 g
bx h
bx i
bx j
bx k
bx l
x="
x<"
x;"
x:"
x9"
x8"
x7"
x6"
x5"
x4"
x3"
x2"
x1"
x0"
x/"
x."
x-"
x,"
x+"
x*"
x)"
x("
x'"
x&"
x%"
x$"
x#"
x""
x!"
x~!
x}!
x|!
x{!
xz!
xy!
xx!
xw!
xv!
xu!
xt!
xs!
xr!
xq!
xp!
xo!
xn!
xm!
xl!
xk!
xj!
xi!
xh!
xg!
xf!
xe!
xd!
0m
1n
0o
0t
0s
0r
0q
0p
0V!
0U!
0T!
0S!
0R!
0Q!
0P!
0O!
0N!
0M!
0L!
0K!
0J!
0I!
0H!
0G!
0F!
0E!
0D!
0C!
0B!
0A!
0@!
0?!
0>!
xc!
xb!
xa!
x`!
x_!
x^!
x]!
x\!
bx >"
x?"
bx @"
0[!
0Z!
0=!
0<!
0;!
0:!
09!
08!
07!
06!
05!
04!
03!
02!
01!
00!
0/!
0.!
0-!
0,!
0+!
0*!
0)!
0(!
0'!
0&!
0%!
0$!
0#!
0"!
0!!
0~
0}
0|
0{
0z
0y
0x
0w
0v
0u
0Y!
0X!
0W!
$end
#5000
1a
0="
0<"
0;"
0:"
09"
08"
07"
06"
05"
04"
03"
02"
01"
00"
0/"
0."
0-"
0,"
0+"
0*"
0)"
0("
0'"
0&"
0%"
0$"
0#"
0""
0!"
0~!
0}!
0|!
0{!
0z!
0y!
0x!
0w!
0v!
0u!
0t!
0s!
0r!
0q!
0p!
0o!
0n!
0m!
0l!
0k!
0j!
0i!
0h!
0g!
0f!
0e!
0d!
1m
0c!
0b!
0a!
0`!
0_!
0^!
0]!
0\!
b0 >"
b100000 @"
#10000
0a
0m
#15000
1a
1m
b100000 @"
#16000
0b
0n
#20000
0a
0m
#25000
1a
1m
#26000
b0 h
b0 k
b0 l
#27000
b1 f
b1 h
b1 k
1[!
#28000
b10 f
b10 h
b10 k
0[!
1Z!
#29000
b11 f
b11 h
b11 k
1[!
#30000
0a
b100 f
b100 h
b100 k
0m
0[!
0Z!
1Y!
#31000
b101 f
b101 h
b101 k
1[!
#32000
b110 f
b110 h
b110 k
0[!
1Z!
#33000
b111 f
b111 h
b111 k
1[!
#34000
b1000 f
b1000 h
b1000 k
0[!
0Z!
0Y!
1X!
#35000
1a
b1001 f
b1001 h
b1001 k
1m
1[!
#36000
b1010 f
b1010 h
b1010 k
0[!
1Z!
#37000
b1011 f
b1011 h
b1011 k
1[!
#38000
b1100 f
b1100 h
b1100 k
0[!
0Z!
1Y!
#39000
b1101 f
b1101 h
b1101 k
1[!
#40000
0a
b1110 f
b1110 h
b1110 k
0m
0[!
1Z!
#41000
b1111 f
b1111 h
b1111 k
1[!
#42000
b10000 f
b10000 h
b10000 k
0[!
0Z!
0Y!
0X!
1W!
#43000
b10001 f
b10001 h
b10001 k
1[!
#44000
b10010 f
b10010 h
b10010 k
0[!
1Z!
#45000
1a
b10011 f
b10011 h
b10011 k
1m
1[!
#46000
b10100 f
b10100 h
b10100 k
0[!
0Z!
1Y!
#47000
b10101 f
b10101 h
b10101 k
1[!
#48000
b10110 f
b10110 h
b10110 k
0[!
1Z!
#49000
b10111 f
b10111 h
b10111 k
1[!
#50000
0a
b11000 f
b11000 h
b11000 k
0m
0[!
0Z!
0Y!
1X!
#51000
b11001 f
b11001 h
b11001 k
1[!
#52000
b11010 f
b11010 h
b11010 k
0[!
1Z!
#53000
b11011 f
b11011 h
b11011 k
1[!
#54000
b11100 f
b11100 h
b11100 k
0[!
0Z!
1Y!
#55000
1a
b11101 f
b11101 h
b11101 k
1m
1[!
#56000
b11110 f
b11110 h
b11110 k
0[!
1Z!
#57000
b11111 f
b11111 h
b11111 k
1[!
#58000
b0 h
b0 i
b1101111010101101101111101110111111001010111111100000000000000000 j
#60000
0a
0m
#65000
1a
1m
#66000
1c
b1101111010101101101111101110111111001010111111100000000000000000 e
1o
1E!
1D!
1C!
1B!
1A!
1@!
1?!
1=!
1;!
18!
17!
16!
15!
14!
13!
11!
10!
1/!
1-!
1,!
1+!
1*!
1)!
1'!
1&!
1$!
1#!
1!!
1}
1{
1z
1y
1x
1v
1u
#70000
0a
0m
#75000
1a
1m
b11011110101011011011111011101111110010101111111000000000000000000000000000000000000000000000000000000000000000000000000000000000000000000000000000000000000000000000000000000000000000000000000000000000000000000000000000000000000000000000000000000000000000000000000000000000000000000000000000000000000000000000000000000000000000000000000000000000000000000000000000000000000000000000000000000000000000000000000000000000000000000000000000000000000000000000000000000000000000000000000000000000000000000000000000000000000000000000000000000000000000000000000000000000000000000000000000000000000000000000000000000000000000000000000000000000000000000000000000000000000000000000000000000000000000000000000000000000000000000000000000000000000000000000000000000000000000000000000000000000000000000000000000000000000000000000000000000000000000000000000000000000000000000000000000000000000000000000000000000000000000000000000000000000000000000000000000000000000000000000000000000000000000000000000000000000000000000000000000000000000000000000000000000000000000000000000000000000000000000000000000000000000000000000000000000000000000000000000000000000000000000000000000000000000000000000000000000000000000000000000000000000000000000000000000000000000000000000000000000000000000000000000000000000000000000000000000000000000000000000000000000000000000000000000000000000000000000000000000000000000000000000000000000000000000000000000000000000000000000000000000000000000000000000000000000000000000000000000000000000000000000000000000000000000000000000000000000000000000000000000000000000000000000000000000000000000000000000000000000000000000000000000000000000000000000000000000000000000000000000000000000000000000000000000000000000000000000000000000000000000000000000000000000000000000000000000000000000000000000000000000000000000000000000000000000000000000000000000000000000000000000000000000000000000000000000000000000000000000000000000000000000000000000000000000000000000000000000000000000000000000000000000000000000000000000000000000000000000000000000000000000000 >"
#76000
0c
b1 h
b1 i
b1101111010101101101111101110111111001010111111100000000000000001 j
0o
#80000
0a
0m
#85000
1a
1m
#86000
1c
b1 d
b1101111010101101101111101110111111001010111111100000000000000001 e
1o
1t
1V!
#90000
0a
0m
#95000
1a
1m
b11011110101011011011111011101111110010101111111000000000000000001101111010101101101111101110111111001010111111100000000000000001000000000000000000000000000000000000000000000000000000000000000000000000000000000000000000000000000000000000000000000000000000000000000000000000000000000000000000000000000000000000000000000000000000000000000000000000000000000000000000000000000000000000000000000000000000000000000000000000000000000000000000000000000000000000000000000000000000000000000000000000000000000000000000000000000000000000000000000000000000000000000000000000000000000000000000000000000000000000000000000000000000000000000000000000000000000000000000000000000000000000000000000000000000000000000000000000000000000000000000000000000000000000000000000000000000000000000000000000000000000000000000000000000000000000000000000000000000000000000000000000000000000000000000000000000000000000000000000000000000000000000000000000000000000000000000000000000000000000000000000000000000000000000000000000000000000000000000000000000000000000000000000000000000000000000000000000000000000000000000000000000000000000000000000000000000000000000000000000000000000000000000000000000000000000000000000000000000000000000000000000000000000000000000000000000000000000000000000000000000000000000000000000000000000000000000000000000000000000000000000000000000000000000000000000000000000000000000000000000000000000000000000000000000000000000000000000000000000000000000000000000000000000000000000000000000000000000000000000000000000000000000000000000000000000000000000000000000000000000000000000000000000000000000000000000000000000000000000000000000000000000000000000000000000000000000000000000000000000000000000000000000000000000000000000000000000000000000000000000000000000000000000000000000000000000000000000000000000000000000000000000000000000000000000000000000000000000000000000000000000000000000000000000000000000000000000000000000000000000000000000000000000000000000000000000000000000000000000000000000000000000000000000000000000000000000000000000000000000000000000000 >"
#96000
0c
b10 h
b10 i
b1101111010101101101111101110111111001010111111100000000000000010 j
0o
#100000
0a
0m
#105000
1a
1m
#106000
1c
b10 d
b1101111010101101101111101110111111001010111111100000000000000010 e
1o
0t
1s
0V!
1U!
#110000
0a
0m
#115000
1a
1m
b11011110101011011011111011101111110010101111111000000000000000001101111010101101101111101110111111001010111111100000000000000001110111101010110110111110111011111100101011111110000000000000001000000000000000000000000000000000000000000000000000000000000000000000000000000000000000000000000000000000000000000000000000000000000000000000000000000000000000000000000000000000000000000000000000000000000000000000000000000000000000000000000000000000000000000000000000000000000000000000000000000000000000000000000000000000000000000000000000000000000000000000000000000000000000000000000000000000000000000000000000000000000000000000000000000000000000000000000000000000000000000000000000000000000000000000000000000000000000000000000000000000000000000000000000000000000000000000000000000000000000000000000000000000000000000000000000000000000000000000000000000000000000000000000000000000000000000000000000000000000000000000000000000000000000000000000000000000000000000000000000000000000000000000000000000000000000000000000000000000000000000000000000000000000000000000000000000000000000000000000000000000000000000000000000000000000000000000000000000000000000000000000000000000000000000000000000000000000000000000000000000000000000000000000000000000000000000000000000000000000000000000000000000000000000000000000000000000000000000000000000000000000000000000000000000000000000000000000000000000000000000000000000000000000000000000000000000000000000000000000000000000000000000000000000000000000000000000000000000000000000000000000000000000000000000000000000000000000000000000000000000000000000000000000000000000000000000000000000000000000000000000000000000000000000000000000000000000000000000000000000000000000000000000000000000000000000000000000000000000000000000000000000000000000000000000000000000000000000000000000000000000000000000000000000000000000000000000000000000000000000000000000000000000000000000000000000000000000000000000000000000000000000000000000000000000000000000000000000000000000000000000000000000000000000000000000000000000000000000000000000000000 >"
#116000
0c
b11 h
b11 i
b1101111010101101101111101110111111001010111111100000000000000011 j
0o
#120000
0a
0m
#125000
1a
1m
#126000
1c
b11 d
b1101111010101101101111101110111111001010111111100000000000000011 e
1o
1t
1V!
#130000
0a
0m
#135000
1a
1m
b11011110101011011011111011101111110010101111111000000000000000001101111010101101101111101110111111001010111111100000000000000001110111101010110110111110111011111100101011111110000000000000001011011110101011011011111011101111110010101111111000000000000000110000000000000000000000000000000000000000000000000000000000000000000000000000000000000000000000000000000000000000000000000000000000000000000000000000000000000000000000000000000000000000000000000000000000000000000000000000000000000000000000000000000000000000000000000000000000000000000000000000000000000000000000000000000000000000000000000000000000000000000000000000000000000000000000000000000000000000000000000000000000000000000000000000000000000000000000000000000000000000000000000000000000000000000000000000000000000000000000000000000000000000000000000000000000000000000000000000000000000000000000000000000000000000000000000000000000000000000000000000000000000000000000000000000000000000000000000000000000000000000000000000000000000000000000000000000000000000000000000000000000000000000000000000000000000000000000000000000000000000000000000000000000000000000000000000000000000000000000000000000000000000000000000000000000000000000000000000000000000000000000000000000000000000000000000000000000000000000000000000000000000000000000000000000000000000000000000000000000000000000000000000000000000000000000000000000000000000000000000000000000000000000000000000000000000000000000000000000000000000000000000000000000000000000000000000000000000000000000000000000000000000000000000000000000000000000000000000000000000000000000000000000000000000000000000000000000000000000000000000000000000000000000000000000000000000000000000000000000000000000000000000000000000000000000000000000000000000000000000000000000000000000000000000000000000000000000000000000000000000000000000000000000000000000000000000000000000000000000000000000000000000000000000000000000000000000000000000000000000000000000000000000000000000000000000000000000000000000000000000000000000000000000000000000000000000000000000000000000000000 >"
#136000
0c
b100 h
b100 i
b1101111010101101101111101110111111001010111111100000000000000100 j
0o
#140000
0a
0m
#145000
1a
1m
#146000
1c
b100 d
b1101111010101101101111101110111111001010111111100000000000000100 e
1o
0t
0s
1r
0V!
0U!
1T!
#150000
0a
0m
#155000
1a
1m
b11011110101011011011111011101111110010101111111000000000000000001101111010101101101111101110111111001010111111100000000000000001110111101010110110111110111011111100101011111110000000000000001011011110101011011011111011101111110010101111111000000000000000111101111010101101101111101110111111001010111111100000000000000100000000000000000000000000000000000000000000000000000000000000000000000000000000000000000000000000000000000000000000000000000000000000000000000000000000000000000000000000000000000000000000000000000000000000000000000000000000000000000000000000000000000000000000000000000000000000000000000000000000000000000000000000000000000000000000000000000000000000000000000000000000000000000000000000000000000000000000000000000000000000000000000000000000000000000000000000000000000000000000000000000000000000000000000000000000000000000000000000000000000000000000000000000000000000000000000000000000000000000000000000000000000000000000000000000000000000000000000000000000000000000000000000000000000000000000000000000000000000000000000000000000000000000000000000000000000000000000000000000000000000000000000000000000000000000000000000000000000000000000000000000000000000000000000000000000000000000000000000000000000000000000000000000000000000000000000000000000000000000000000000000000000000000000000000000000000000000000000000000000000000000000000000000000000000000000000000000000000000000000000000000000000000000000000000000000000000000000000000000000000000000000000000000000000000000000000000000000000000000000000000000000000000000000000000000000000000000000000000000000000000000000000000000000000000000000000000000000000000000000000000000000000000000000000000000000000000000000000000000000000000000000000000000000000000000000000000000000000000000000000000000000000000000000000000000000000000000000000000000000000000000000000000000000000000000000000000000000000000000000000000000000000000000000000000000000000000000000000000000000000000000000000000000000000000000000000000000000000000000000000000000000000000000000000000000000000000000000000000 >"
#156000
0c
b101 h
b101 i
b1101111010101101101111101110111111001010111111100000000000000101 j
0o
#160000
0a
0m
#165000
1a
1m
#166000
1c
b101 d
b1101111010101101101111101110111111001010111111100000000000000101 e
1o
1t
1V!
#170000
0a
0m
#175000
1a
1m
b11011110101011011011111011101111110010101111111000000000000000001101111010101101101111101110111111001010111111100000000000000001110111101010110110111110111011111100101011111110000000000000001011011110101011011011111011101111110010101111111000000000000000111101111010101101101111101110111111001010111111100000000000000100110111101010110110111110111011111100101011111110000000000000010100000000000000000000000000000000000000000000000000000000000000000000000000000000000000000000000000000000000000000000000000000000000000000000000000000000000000000000000000000000000000000000000000000000000000000000000000000000000000000000000000000000000000000000000000000000000000000000000000000000000000000000000000000000000000000000000000000000000000000000000000000000000000000000000000000000000000000000000000000000000000000000000000000000000000000000000000000000000000000000000000000000000000000000000000000000000000000000000000000000000000000000000000000000000000000000000000000000000000000000000000000000000000000000000000000000000000000000000000000000000000000000000000000000000000000000000000000000000000000000000000000000000000000000000000000000000000000000000000000000000000000000000000000000000000000000000000000000000000000000000000000000000000000000000000000000000000000000000000000000000000000000000000000000000000000000000000000000000000000000000000000000000000000000000000000000000000000000000000000000000000000000000000000000000000000000000000000000000000000000000000000000000000000000000000000000000000000000000000000000000000000000000000000000000000000000000000000000000000000000000000000000000000000000000000000000000000000000000000000000000000000000000000000000000000000000000000000000000000000000000000000000000000000000000000000000000000000000000000000000000000000000000000000000000000000000000000000000000000000000000000000000000000000000000000000000000000000000000000000000000000000000000000000000000000000000000000000000000000000000000000000000000000000000000000000000000000000000000000000000000000000000000000000000000000000000000000000000 >"
#176000
0c
b110 h
b110 i
b1101111010101101101111101110111111001010111111100000000000000110 j
0o
#180000
0a
0m
#185000
1a
1m
#186000
1c
b110 d
b1101111010101101101111101110111111001010111111100000000000000110 e
1o
0t
1s
0V!
1U!
#190000
0a
0m
